<?xml version="1.0" encoding="UTF-8"?>
<MF0 version="1.1" packageUris="http://schema.mathworks.com/mf0/ci/19700101 http://schema.mathworks.com/mf0/sl_modelref_info/R2022a http://schema.mathworks.com/mf0/slexec_mm_sto/R2022a_202107291127">
  <ModelRefInfoRepo.ModelRefInfoRoot type="ModelRefInfoRepo.ModelRefInfoRoot" uuid="3f0a1d5c-180d-4e43-befa-d2dc20f227ec">
    <allEdges type="ModelRefInfoRepo.SampleTimeGraphEdge" uuid="1d8f778d-164d-457a-b559-9905e8f50043">
      <dstNodeIdx>1</dstNodeIdx>
    </allEdges>
    <allEdges type="ModelRefInfoRepo.SampleTimeGraphEdge" uuid="6e08a8b6-c369-4d5a-b387-179b7a152e25">
      <dstNodeIdx>2</dstNodeIdx>
    </allEdges>
    <allEdges type="ModelRefInfoRepo.SampleTimeGraphEdge" uuid="9ee5c3d9-17fb-4008-93c1-98b0bdd61360">
      <dstNodeIdx>3</dstNodeIdx>
    </allEdges>
    <allEdges type="ModelRefInfoRepo.SampleTimeGraphEdge" uuid="50e16be1-c7eb-416b-bf18-a1bbfc03fdde">
      <dstNodeIdx>4</dstNodeIdx>
    </allEdges>
    <allEdges type="ModelRefInfoRepo.SampleTimeGraphEdge" uuid="512ae055-8b3a-4e18-889f-37c28f41a5d8">
      <dstNodeIdx>5</dstNodeIdx>
    </allEdges>
    <allEdges type="ModelRefInfoRepo.SampleTimeGraphEdge" uuid="7f0a18f6-1e43-425d-b940-c14999bee576">
      <dstNodeIdx>6</dstNodeIdx>
    </allEdges>
    <allEdges type="ModelRefInfoRepo.SampleTimeGraphEdge" uuid="6407d5b6-19c6-47ff-b192-0ccd8714c9b9">
      <dstNodeIdx>7</dstNodeIdx>
    </allEdges>
    <allEdges type="ModelRefInfoRepo.SampleTimeGraphEdge" uuid="d2a54e2d-a7ce-471d-af2f-294cb398fda5">
      <dstNodeIdx>8</dstNodeIdx>
    </allEdges>
    <allEdges type="ModelRefInfoRepo.SampleTimeGraphEdge" uuid="e7252218-ac72-4638-bb75-4c6e7a691e00">
      <dstNodeIdx>9</dstNodeIdx>
    </allEdges>
    <allEdges type="ModelRefInfoRepo.SampleTimeGraphEdge" uuid="3df257a4-76d1-4f95-9fbb-d6109dfd5b1b">
      <dstNodeIdx>10</dstNodeIdx>
    </allEdges>
    <allEdges type="ModelRefInfoRepo.SampleTimeGraphEdge" uuid="b869cf8c-2f44-4e8b-bbfb-5d9763019640">
      <dstNodeIdx>11</dstNodeIdx>
    </allEdges>
    <allEdges type="ModelRefInfoRepo.SampleTimeGraphEdge" uuid="cbbfebf8-5636-456d-a5b5-eafc205d012d">
      <dstNodeIdx>12</dstNodeIdx>
    </allEdges>
    <allEdges type="ModelRefInfoRepo.SampleTimeGraphEdge" uuid="0b6a4692-42a3-4a9f-bfd8-66f9daedfe9f">
      <dstNodeIdx>13</dstNodeIdx>
    </allEdges>
    <allEdges type="ModelRefInfoRepo.SampleTimeGraphEdge" uuid="75cf5bb0-38dd-42f7-a864-e1701dce06b0">
      <dstNodeIdx>14</dstNodeIdx>
    </allEdges>
    <allEdges type="ModelRefInfoRepo.SampleTimeGraphEdge" uuid="a87d0e3b-23d6-4f0e-9df0-e775a136ce61">
      <dstNodeIdx>15</dstNodeIdx>
    </allEdges>
    <allEdges type="ModelRefInfoRepo.SampleTimeGraphEdge" uuid="c04bc5bc-96e6-4d1a-87e6-a1ac0449164c">
      <dstNodeIdx>16</dstNodeIdx>
    </allEdges>
    <allEdges type="ModelRefInfoRepo.SampleTimeGraphEdge" uuid="b1b3308a-aa31-4bf1-8917-af03a18f9de3">
      <dstNodeIdx>17</dstNodeIdx>
    </allEdges>
    <allEdges type="ModelRefInfoRepo.SampleTimeGraphEdge" uuid="f9d7dcd4-f4c9-44bf-81be-f4eb7b6296db">
      <dstNodeIdx>18</dstNodeIdx>
    </allEdges>
    <allEdges type="ModelRefInfoRepo.SampleTimeGraphEdge" uuid="1a2ac38e-7bf2-4e4b-89f4-41bc12a7e6ca">
      <dstNodeIdx>19</dstNodeIdx>
    </allEdges>
    <allEdges type="ModelRefInfoRepo.SampleTimeGraphEdge" uuid="fd691db4-6950-434e-a880-19151dc6af7a">
      <dstNodeIdx>20</dstNodeIdx>
    </allEdges>
    <allEdges type="ModelRefInfoRepo.SampleTimeGraphEdge" uuid="f6e33aff-8b12-4569-a6a7-2ff693b0e788">
      <dstNodeIdx>21</dstNodeIdx>
    </allEdges>
    <allEdges type="ModelRefInfoRepo.SampleTimeGraphEdge" uuid="4064bf5c-448f-4af5-ac7e-92b34b01d27e">
      <dstNodeIdx>22</dstNodeIdx>
    </allEdges>
    <allEdges type="ModelRefInfoRepo.SampleTimeGraphEdge" uuid="866b0aa3-0ca0-43f0-a91b-8738d5dd5043">
      <dstNodeIdx>23</dstNodeIdx>
    </allEdges>
    <allEdges type="ModelRefInfoRepo.SampleTimeGraphEdge" uuid="84c2a4a3-648f-4666-8e20-1f622e28da65">
      <dstNodeIdx>24</dstNodeIdx>
    </allEdges>
    <allEdges type="ModelRefInfoRepo.SampleTimeGraphEdge" uuid="d174a7af-d041-4790-b3c2-1abaff68b5e7">
      <dstNodeIdx>25</dstNodeIdx>
    </allEdges>
    <allEdges type="ModelRefInfoRepo.SampleTimeGraphEdge" uuid="283dc471-dfcf-49ab-96da-cc99f08ee30f">
      <dstNodeIdx>26</dstNodeIdx>
    </allEdges>
    <allEdges type="ModelRefInfoRepo.SampleTimeGraphEdge" uuid="9c4f540d-227e-4e50-83d6-e74f049171d8">
      <dstNodeIdx>27</dstNodeIdx>
    </allEdges>
    <allEdges type="ModelRefInfoRepo.SampleTimeGraphEdge" uuid="5c79a9aa-c303-40fe-913e-919a5484ef04">
      <dstNodeIdx>28</dstNodeIdx>
    </allEdges>
    <allEdges type="ModelRefInfoRepo.SampleTimeGraphEdge" uuid="83a39257-64e8-449e-8574-49e651ae3dfe">
      <dstNodeIdx>29</dstNodeIdx>
    </allEdges>
    <allEdges type="ModelRefInfoRepo.SampleTimeGraphEdge" uuid="5a8ba7fb-10e4-4790-a785-f21be20b5e0c">
      <dstNodeIdx>30</dstNodeIdx>
    </allEdges>
    <allEdges type="ModelRefInfoRepo.SampleTimeGraphEdge" uuid="34ff2ecb-048a-4709-b851-a58d61420b3b">
      <dstNodeIdx>31</dstNodeIdx>
    </allEdges>
    <allEdges type="ModelRefInfoRepo.SampleTimeGraphEdge" uuid="0dc220bc-3704-4054-9ac4-d9b8a7ca47fb">
      <dstNodeIdx>32</dstNodeIdx>
    </allEdges>
    <allEdges type="ModelRefInfoRepo.SampleTimeGraphEdge" uuid="9f0532d3-3faa-4124-b06a-359e897a88f3">
      <dstNodeIdx>33</dstNodeIdx>
    </allEdges>
    <allEdges type="ModelRefInfoRepo.SampleTimeGraphEdge" uuid="b7af68ae-49c8-4132-beaa-c27e06f19e25">
      <dstNodeIdx>34</dstNodeIdx>
    </allEdges>
    <allEdges type="ModelRefInfoRepo.SampleTimeGraphEdge" uuid="21c06f47-dcaf-477a-9460-f9f8170c58a8">
      <dstNodeIdx>35</dstNodeIdx>
    </allEdges>
    <calibrationData type="ModelRefInfoRepo.CalibrationData" uuid="ee0ef200-97cb-454d-a842-817a465e1be5">
      <InternalData>[{&quot;Name&quot;:&quot;&quot;,&quot;Profile&quot;:&quot;&quot;},{&quot;Name&quot;:&quot;&quot;,&quot;Profile&quot;:&quot;&quot;},{&quot;Name&quot;:&quot;&quot;,&quot;Profile&quot;:&quot;&quot;},{&quot;Name&quot;:&quot;&quot;,&quot;Profile&quot;:&quot;&quot;},{&quot;Name&quot;:&quot;&quot;,&quot;Profile&quot;:&quot;&quot;},{&quot;Name&quot;:&quot;&quot;,&quot;Profile&quot;:&quot;&quot;},{&quot;Name&quot;:&quot;&quot;,&quot;Profile&quot;:&quot;&quot;},{&quot;Name&quot;:&quot;&quot;,&quot;Profile&quot;:&quot;&quot;},{&quot;Name&quot;:&quot;&quot;,&quot;Profile&quot;:&quot;&quot;},{&quot;Name&quot;:&quot;&quot;,&quot;Profile&quot;:&quot;&quot;},{&quot;Name&quot;:&quot;&quot;,&quot;Profile&quot;:&quot;&quot;},{&quot;Name&quot;:&quot;&quot;,&quot;Profile&quot;:&quot;&quot;},{&quot;Name&quot;:&quot;&quot;,&quot;Profile&quot;:&quot;&quot;},{&quot;Name&quot;:&quot;&quot;,&quot;Profile&quot;:&quot;&quot;},{&quot;Name&quot;:&quot;&quot;,&quot;Profile&quot;:&quot;&quot;},{&quot;Name&quot;:&quot;&quot;,&quot;Profile&quot;:&quot;&quot;},{&quot;Name&quot;:&quot;E03_DHM_L&quot;,&quot;Profile&quot;:&quot;&quot;}]</InternalData>
      <ModelName>DHM</ModelName>
      <RootIOData>[{&quot;Name&quot;:&quot;VeINP_CAN_PowerMode_sig_VeINP_CAN_PowerMode_sig&quot;,&quot;Profile&quot;:&quot;&quot;},{&quot;Name&quot;:&quot;VeOUT_DLK_LHFDoorLockSts_sig_VeOUT_DLK_LHFDoorLockSts_sig&quot;,&quot;Profile&quot;:&quot;&quot;},{&quot;Name&quot;:&quot;VeOUT_SP_EspVehSpd_kmh_VeOUT_SP_EspVehSpd_kmh&quot;,&quot;Profile&quot;:&quot;&quot;},{&quot;Name&quot;:&quot;VsINP_HWA_DriverHandleHall_sig_VsINP_HWA_DriverHandleHall_sig&quot;,&quot;Profile&quot;:&quot;&quot;},{&quot;Name&quot;:&quot;VsINP_HWA_RLHandleHall_sig_VsINP_HWA_RLHandleHall_sig&quot;,&quot;Profile&quot;:&quot;&quot;},{&quot;Name&quot;:&quot;VeINP_CAN_FRDoorHandleSts_sig_VeINP_CAN_FRDoorHandleSts_sig&quot;,&quot;Profile&quot;:&quot;&quot;},{&quot;Name&quot;:&quot;VeINP_CAN_RRDoorHandleSts_sig_VeINP_CAN_RRDoorHandleSts_sig&quot;,&quot;Profile&quot;:&quot;&quot;},{&quot;Name&quot;:&quot;VeOUT_SP_LHFdoorSts_sig_VeOUT_SP_LHFdoorSts_sig&quot;,&quot;Profile&quot;:&quot;&quot;},{&quot;Name&quot;:&quot;VeOUT_SP_LHRdoorSts_sig_VeOUT_SP_LHRdoorSts_sig&quot;,&quot;Profile&quot;:&quot;&quot;},{&quot;Name&quot;:&quot;VeINP_CAN_RHFDoorSts_sig_VeINP_CAN_RHFDoorSts_sig&quot;,&quot;Profile&quot;:&quot;&quot;},{&quot;Name&quot;:&quot;VeINP_CAN_RHRDoorSts_sig_VeINP_CAN_RHRDoorSts_sig&quot;,&quot;Profile&quot;:&quot;&quot;},{&quot;Name&quot;:&quot;VbOUT_SP_CrashOutpSts_flg_VbOUT_SP_CrashOutpSts_flg&quot;,&quot;Profile&quot;:&quot;&quot;},{&quot;Name&quot;:&quot;VsINP_EPRM_FLDoorHandleFromEE_sig_VsINP_EPRM_FLDoorHandleFromEE_sig&quot;,&quot;Profile&quot;:&quot;&quot;},{&quot;Name&quot;:&quot;VsINP_EPRM_RLDoorHandleFromEE_sig_VsINP_EPRM_RLDoorHandleFromEE_sig&quot;,&quot;Profile&quot;:&quot;&quot;},{&quot;Name&quot;:&quot;VeINP_EPRM_FLDoorHandleLrnStsEE_sig_VeINP_EPRM_FLDoorHandleLrnStsEE_sig&quot;,&quot;Profile&quot;:&quot;&quot;},{&quot;Name&quot;:&quot;VeINP_EPRM_RLDoorHandleLrnStsEE_sig_VeINP_EPRM_RLDoorHandleLrnStsEE_sig&quot;,&quot;Profile&quot;:&quot;&quot;},{&quot;Name&quot;:&quot;VeINP_CAN_FRDoorHandleLrnSts_sig_VeINP_CAN_FRDoorHandleLrnSts_sig&quot;,&quot;Profile&quot;:&quot;&quot;},{&quot;Name&quot;:&quot;VeINP_CAN_RRDoorHandleLrnSts_sig_VeINP_CAN_RRDoorHandleLrnSts_sig&quot;,&quot;Profile&quot;:&quot;&quot;},{&quot;Name&quot;:&quot;VbINP_HWA_DoorHandleLrnReq_flg_VbINP_HWA_DoorHandleLrnReq_flg&quot;,&quot;Profile&quot;:&quot;&quot;},{&quot;Name&quot;:&quot;VeOUT_DHM_FLHandleFoldedStatus_sig_VeOUT_DHM_FLHandleFoldedStatus_sig&quot;,&quot;Profile&quot;:&quot;&quot;},{&quot;Name&quot;:&quot;VeOUT_DHM_RLHandleFoldedStatus_sig_VeOUT_DHM_RLHandleFoldedStatus_sig&quot;,&quot;Profile&quot;:&quot;&quot;},{&quot;Name&quot;:&quot;VeOUT_DHM_FRHandleFoldedStatus_sig_VeOUT_DHM_FRHandleFoldedStatus_sig&quot;,&quot;Profile&quot;:&quot;&quot;},{&quot;Name&quot;:&quot;VeOUT_DHM_RRHandleFoldedStatus_sig_VeOUT_DHM_RRHandleFoldedStatus_sig&quot;,&quot;Profile&quot;:&quot;&quot;},{&quot;Name&quot;:&quot;VeOUT_DHM_FRDoorHandleReq_sig_VeOUT_DHM_FRDoorHandleReq_sig&quot;,&quot;Profile&quot;:&quot;&quot;},{&quot;Name&quot;:&quot;VeOUT_DHM_RRDoorHandleReq_sig_VeOUT_DHM_RRDoorHandleReq_sig&quot;,&quot;Profile&quot;:&quot;&quot;},{&quot;Name&quot;:&quot;VbOUT_DHM_FLHadUnfold_flg_VbOUT_DHM_FLHadUnfold_flg&quot;,&quot;Profile&quot;:&quot;&quot;},{&quot;Name&quot;:&quot;VbOUT_DHM_FLHadFold_flg_VbOUT_DHM_FLHadFold_flg&quot;,&quot;Profile&quot;:&quot;&quot;},{&quot;Name&quot;:&quot;VbOUT_DHM_RLHandleUnfold_flg_VbOUT_DHM_RLHandleUnfold_flg&quot;,&quot;Profile&quot;:&quot;&quot;},{&quot;Name&quot;:&quot;VbOUT_DHM_RLHandleFold_flg_VbOUT_DHM_RLHandleFold_flg&quot;,&quot;Profile&quot;:&quot;&quot;},{&quot;Name&quot;:&quot;VsINP_DHM_FLDoorHandleEE_sig_VsINP_DHM_FLDoorHandleEE_sig&quot;,&quot;Profile&quot;:&quot;&quot;},{&quot;Name&quot;:&quot;VsINP_DHM_RLDoorHandleEE_sig_VsINP_DHM_RLDoorHandleEE_sig&quot;,&quot;Profile&quot;:&quot;&quot;},{&quot;Name&quot;:&quot;VeOUT_DHM_DoorHandleLrnSts_sig_VeOUT_DHM_DoorHandleLrnSts_sig&quot;,&quot;Profile&quot;:&quot;&quot;},{&quot;Name&quot;:&quot;VeOUT_DHM_FLDoorHandleLrnStsEE_sig_VeOUT_DHM_FLDoorHandleLrnStsEE_sig&quot;,&quot;Profile&quot;:&quot;&quot;},{&quot;Name&quot;:&quot;VeOUT_DHM_RLDoorHandleLrnStsEE_sig_VeOUT_DHM_RLDoorHandleLrnStsEE_sig&quot;,&quot;Profile&quot;:&quot;&quot;},{&quot;Name&quot;:&quot;VbOUT_DHM_DoorHandleLrnReq_flg_VbOUT_DHM_DoorHandleLrnReq_flg&quot;,&quot;Profile&quot;:&quot;&quot;}]</RootIOData>
    </calibrationData>
    <childModelRefInfo type="ModelRefInfoRepo.ChildModelRefInfo" uuid="db766670-f8f4-4de3-a53e-f7318ffe0314">
      <isSingleInstance>true</isSingleInstance>
      <modelName>DHM</modelName>
      <modelPath>DHM</modelPath>
    </childModelRefInfo>
    <containsInitResetTermSampleTimes>true</containsInitResetTermSampleTimes>
    <dataDictionary>DHM.sldd</dataDictionary>
    <dataDictionarySet>DHM.sldd</dataDictionarySet>
    <dataDictionarySetForDataTypeCheck>DHM.sldd</dataDictionarySetForDataTypeCheck>
    <dataTransferInfos>AAFJTQAAAAAOAAAAOAAAAAYAAAAIAAAAAgAAAAAAAAAFAAAACAAAAAAAAAABAAAAAQAAAAAAAAAFAAQAAQAAAAEAAAAAAAAA</dataTransferInfos>
    <defaultsCMapping>{&quot;Inports&quot;:&quot;{\&quot;Name\&quot;:\&quot;Default\&quot;,\&quot;Checksum\&quot;:\&quot;Default\&quot;,\&quot;PerInstancePropertiesChecksum\&quot;:\&quot;\&quot;,\&quot;MemorySectionName\&quot;:\&quot;None\&quot;,\&quot;MemorySectionChecksum\&quot;:\&quot;None\&quot;}&quot;,&quot;Outports&quot;:&quot;{\&quot;Name\&quot;:\&quot;Default\&quot;,\&quot;Checksum\&quot;:\&quot;Default\&quot;,\&quot;PerInstancePropertiesChecksum\&quot;:\&quot;\&quot;,\&quot;MemorySectionName\&quot;:\&quot;None\&quot;,\&quot;MemorySectionChecksum\&quot;:\&quot;None\&quot;}&quot;,&quot;ParameterArguments&quot;:&quot;{\&quot;Name\&quot;:\&quot;Default\&quot;,\&quot;Checksum\&quot;:\&quot;Default\&quot;,\&quot;PerInstancePropertiesChecksum\&quot;:\&quot;\&quot;,\&quot;MemorySectionName\&quot;:\&quot;None\&quot;,\&quot;MemorySectionChecksum\&quot;:\&quot;None\&quot;}&quot;,&quot;LocalParameters&quot;:&quot;{\&quot;Name\&quot;:\&quot;Default\&quot;,\&quot;Checksum\&quot;:\&quot;Default\&quot;,\&quot;PerInstancePropertiesChecksum\&quot;:\&quot;\&quot;,\&quot;MemorySectionName\&quot;:\&quot;None\&quot;,\&quot;MemorySectionChecksum\&quot;:\&quot;None\&quot;}&quot;,&quot;GlobalParameters&quot;:&quot;{\&quot;Name\&quot;:\&quot;Default\&quot;,\&quot;Checksum\&quot;:\&quot;Default\&quot;,\&quot;PerInstancePropertiesChecksum\&quot;:\&quot;\&quot;,\&quot;MemorySectionName\&quot;:\&quot;None\&quot;,\&quot;MemorySectionChecksum\&quot;:\&quot;None\&quot;}&quot;,&quot;InternalData&quot;:&quot;{\&quot;Name\&quot;:\&quot;Default\&quot;,\&quot;Checksum\&quot;:\&quot;Default\&quot;,\&quot;PerInstancePropertiesChecksum\&quot;:\&quot;\&quot;,\&quot;MemorySectionName\&quot;:\&quot;None\&quot;,\&quot;MemorySectionChecksum\&quot;:\&quot;None\&quot;}&quot;,&quot;SharedLocalDataStores&quot;:&quot;{\&quot;Name\&quot;:\&quot;Default\&quot;,\&quot;Checksum\&quot;:\&quot;Default\&quot;,\&quot;PerInstancePropertiesChecksum\&quot;:\&quot;\&quot;,\&quot;MemorySectionName\&quot;:\&quot;None\&quot;,\&quot;MemorySectionChecksum\&quot;:\&quot;None\&quot;}&quot;,&quot;GlobalDataStores&quot;:&quot;{\&quot;Name\&quot;:\&quot;Default\&quot;,\&quot;Checksum\&quot;:\&quot;Default\&quot;,\&quot;PerInstancePropertiesChecksum\&quot;:\&quot;\&quot;,\&quot;MemorySectionName\&quot;:\&quot;None\&quot;,\&quot;MemorySectionChecksum\&quot;:\&quot;None\&quot;}&quot;,&quot;Constants&quot;:&quot;{\&quot;Name\&quot;:\&quot;Default\&quot;,\&quot;Checksum\&quot;:\&quot;Default\&quot;,\&quot;PerInstancePropertiesChecksum\&quot;:\&quot;\&quot;,\&quot;MemorySectionName\&quot;:\&quot;None\&quot;,\&quot;MemorySectionChecksum\&quot;:\&quot;None\&quot;}&quot;,&quot;DataTransfers&quot;:&quot;{\&quot;Name\&quot;:\&quot;Default\&quot;,\&quot;Checksum\&quot;:\&quot;Default\&quot;,\&quot;PerInstancePropertiesChecksum\&quot;:\&quot;\&quot;,\&quot;MemorySectionName\&quot;:\&quot;None\&quot;,\&quot;MemorySectionChecksum\&quot;:\&quot;None\&quot;}&quot;,&quot;ModelData&quot;:&quot;{\&quot;Name\&quot;:\&quot;Default\&quot;,\&quot;Checksum\&quot;:\&quot;Default\&quot;,\&quot;PerInstancePropertiesChecksum\&quot;:\&quot;\&quot;,\&quot;MemorySectionName\&quot;:\&quot;None\&quot;,\&quot;MemorySectionChecksum\&quot;:\&quot;None\&quot;}&quot;,&quot;InitializeTerminate&quot;:&quot;{\&quot;Name\&quot;:\&quot;Default\&quot;,\&quot;Checksum\&quot;:\&quot;Default\&quot;,\&quot;PerInstancePropertiesChecksum\&quot;:\&quot;\&quot;,\&quot;MemorySectionName\&quot;:\&quot;None\&quot;,\&quot;MemorySectionChecksum\&quot;:\&quot;None\&quot;}&quot;,&quot;Execution&quot;:&quot;{\&quot;Name\&quot;:\&quot;Default\&quot;,\&quot;Checksum\&quot;:\&quot;Default\&quot;,\&quot;PerInstancePropertiesChecksum\&quot;:\&quot;\&quot;,\&quot;MemorySectionName\&quot;:\&quot;None\&quot;,\&quot;MemorySectionChecksum\&quot;:\&quot;None\&quot;}&quot;,&quot;SharedUtility&quot;:&quot;{\&quot;Name\&quot;:\&quot;Default\&quot;,\&quot;Checksum\&quot;:\&quot;Default\&quot;,\&quot;PerInstancePropertiesChecksum\&quot;:\&quot;\&quot;,\&quot;MemorySectionName\&quot;:\&quot;None\&quot;,\&quot;MemorySectionChecksum\&quot;:\&quot;None\&quot;}&quot;}</defaultsCMapping>
    <fcnCallPortGroups type="ModelRefInfoRepo.FcnCallPortGroup" uuid="2c31fd58-8e11-42ef-869e-57d535f88f71">
      <hasDisableMethod>true</hasDisableMethod>
      <hasEnableMethod>true</hasEnableMethod>
      <hasTaskPriority>true</hasTaskPriority>
      <isAsync>true</isAsync>
      <isPeriodicFcnCall>true</isPeriodicFcnCall>
      <schedulingPriority>2147483647</schedulingPriority>
      <taskPriority>40</taskPriority>
      <tid>1</tid>
      <compDataInputPorts>1</compDataInputPorts>
      <compDataInputPorts>2</compDataInputPorts>
      <compDataInputPorts>3</compDataInputPorts>
      <compDataInputPorts>4</compDataInputPorts>
      <compDataInputPorts>5</compDataInputPorts>
      <compDataInputPorts>6</compDataInputPorts>
      <compDataInputPorts>7</compDataInputPorts>
      <compDataInputPorts>8</compDataInputPorts>
      <compDataInputPorts>9</compDataInputPorts>
      <compDataInputPorts>10</compDataInputPorts>
      <compDataInputPorts>11</compDataInputPorts>
      <compDataInputPorts>12</compDataInputPorts>
      <compDataInputPorts>13</compDataInputPorts>
      <compDataInputPorts>14</compDataInputPorts>
      <compDataInputPorts>15</compDataInputPorts>
      <compDataInputPorts>16</compDataInputPorts>
      <compDataInputPorts>17</compDataInputPorts>
      <compDataInputPorts>18</compDataInputPorts>
      <compDataInputPorts>19</compDataInputPorts>
      <compDataOutputPorts>0</compDataOutputPorts>
      <compDataOutputPorts>1</compDataOutputPorts>
      <compDataOutputPorts>2</compDataOutputPorts>
      <compDataOutputPorts>3</compDataOutputPorts>
      <compDataOutputPorts>4</compDataOutputPorts>
      <compDataOutputPorts>5</compDataOutputPorts>
      <compDataOutputPorts>6</compDataOutputPorts>
      <compDataOutputPorts>7</compDataOutputPorts>
      <compDataOutputPorts>8</compDataOutputPorts>
      <compDataOutputPorts>9</compDataOutputPorts>
      <compDataOutputPorts>10</compDataOutputPorts>
      <compDataOutputPorts>11</compDataOutputPorts>
      <compDataOutputPorts>12</compDataOutputPorts>
      <compDataOutputPorts>13</compDataOutputPorts>
      <compDataOutputPorts>14</compDataOutputPorts>
      <compDataOutputPorts>15</compDataOutputPorts>
      <dataInputPorts>1</dataInputPorts>
      <dataInputPorts>2</dataInputPorts>
      <dataInputPorts>3</dataInputPorts>
      <dataInputPorts>4</dataInputPorts>
      <dataInputPorts>5</dataInputPorts>
      <dataInputPorts>6</dataInputPorts>
      <dataInputPorts>7</dataInputPorts>
      <dataInputPorts>8</dataInputPorts>
      <dataInputPorts>9</dataInputPorts>
      <dataInputPorts>10</dataInputPorts>
      <dataInputPorts>11</dataInputPorts>
      <dataInputPorts>12</dataInputPorts>
      <dataInputPorts>13</dataInputPorts>
      <dataInputPorts>14</dataInputPorts>
      <dataInputPorts>15</dataInputPorts>
      <dataInputPorts>16</dataInputPorts>
      <dataInputPorts>17</dataInputPorts>
      <dataInputPorts>18</dataInputPorts>
      <dataInputPorts>19</dataInputPorts>
      <dataOutputPorts>0</dataOutputPorts>
      <dataOutputPorts>1</dataOutputPorts>
      <dataOutputPorts>2</dataOutputPorts>
      <dataOutputPorts>3</dataOutputPorts>
      <dataOutputPorts>4</dataOutputPorts>
      <dataOutputPorts>5</dataOutputPorts>
      <dataOutputPorts>6</dataOutputPorts>
      <dataOutputPorts>7</dataOutputPorts>
      <dataOutputPorts>8</dataOutputPorts>
      <dataOutputPorts>9</dataOutputPorts>
      <dataOutputPorts>10</dataOutputPorts>
      <dataOutputPorts>11</dataOutputPorts>
      <dataOutputPorts>12</dataOutputPorts>
      <dataOutputPorts>13</dataOutputPorts>
      <dataOutputPorts>14</dataOutputPorts>
      <dataOutputPorts>15</dataOutputPorts>
      <preCompRateSpec type="ModelRefInfoRepo.RateSpec" uuid="494e0c90-c4b9-494a-be5b-8e63252cb2ae">
        <period>.01</period>
      </preCompRateSpec>
      <simulinkFunctionName type="ModelRefInfoRepo.QualifiedFunctionName" uuid="42cf28df-604a-4655-bbed-cb0e5c11512b"/>
    </fcnCallPortGroups>
    <fundamentalSampleTimePeriod>.01</fundamentalSampleTimePeriod>
    <globalVariables>Boolean</globalVariables>
    <globalVariables>SInt16</globalVariables>
    <globalVariables>UInt8</globalVariables>
    <hasBlockWithPeriodicDiscreteSampleTime>true</hasBlockWithPeriodicDiscreteSampleTime>
    <hasBwsAccessed>true</hasBwsAccessed>
    <hasBwsAccessedByAnyModel>true</hasBwsAccessedByAnyModel>
    <hasNonVirtualConstantTs>true</hasNonVirtualConstantTs>
    <hasStatesModifiedInOutputUpdate>true</hasStatesModifiedInOutputUpdate>
    <inports type="ModelRefInfoRepo.InportInformation" uuid="67435394-d435-4066-8fff-08a90e7dab94">
      <hasSystemInitMethod>true</hasSystemInitMethod>
      <isFunctionCallInitiator>true</isFunctionCallInitiator>
      <isNotDerivPort>true</isNotDerivPort>
      <designMax>Inf</designMax>
      <designMin>-Inf</designMin>
      <indexType>2</indexType>
      <rateInfos type="ModelRefInfoRepo.RateInfo">
        <compiled>true</compiled>
        <period>.01</period>
        <priority>41</priority>
        <rateIdx>1</rateIdx>
        <taskedExplicitly>true</taskedExplicitly>
      </rateInfos>
      <resolvedSignalObject></resolvedSignalObject>
      <autosarInfo type="ModelRefInfoRepo.AUTOSARInportInfo" uuid="50b23324-85e7-4099-85ac-1b631381358a"/>
      <executionInterface type="ModelRefInfoRepo.InputExecutionInterface" uuid="cbc614b8-3e2e-4c5e-a47b-5a883046a758"/>
      <sigNameToEMVCEMap type="ModelRefInfoRepo.SigNameEMVCEInfo" uuid="abd703cb-7d28-411e-8596-cd899ec666f8"/>
    </inports>
    <inports type="ModelRefInfoRepo.InportInformation" uuid="630df5fc-6f63-459b-8c35-df57b848511b">
      <isNotDerivPort>true</isNotDerivPort>
      <designMax>Inf</designMax>
      <designMin>-Inf</designMin>
      <indexType>2</indexType>
      <originalPortNumber>1</originalPortNumber>
      <rateInfos type="ModelRefInfoRepo.RateInfo">
        <compiled>true</compiled>
        <period>.01</period>
        <priority>41</priority>
        <rateIdx>1</rateIdx>
        <taskedExplicitly>true</taskedExplicitly>
      </rateInfos>
      <resolvedSignalObject></resolvedSignalObject>
      <autosarInfo type="ModelRefInfoRepo.AUTOSARInportInfo" uuid="4afeed3b-0924-43ce-90fa-5aeb8833f31e">
        <ElementName>VeINP_CAN_PowerMode_sig</ElementName>
        <PortName>VeINP_CAN_PowerMode_sig</PortName>
      </autosarInfo>
      <executionInterface type="ModelRefInfoRepo.InputExecutionInterface" uuid="a55f665c-1749-42f8-b096-094da781b2b3"/>
      <sigNameToEMVCEMap type="ModelRefInfoRepo.SigNameEMVCEInfo" uuid="dfb2b06e-e8a8-42af-a72f-c9cca6a75777"/>
    </inports>
    <inports type="ModelRefInfoRepo.InportInformation" uuid="fb967e84-4743-4c5a-802a-a517b2764e90">
      <isNotDerivPort>true</isNotDerivPort>
      <designMax>Inf</designMax>
      <designMin>-Inf</designMin>
      <indexType>2</indexType>
      <originalPortNumber>2</originalPortNumber>
      <rateInfos type="ModelRefInfoRepo.RateInfo">
        <compiled>true</compiled>
        <period>.01</period>
        <priority>41</priority>
        <rateIdx>1</rateIdx>
        <taskedExplicitly>true</taskedExplicitly>
      </rateInfos>
      <resolvedSignalObject></resolvedSignalObject>
      <autosarInfo type="ModelRefInfoRepo.AUTOSARInportInfo" uuid="a69f4318-a7da-41ca-b205-5ed23d1aea68">
        <ElementName>VeOUT_DLK_LHFDoorLockSts_sig</ElementName>
        <PortName>VeOUT_DLK_LHFDoorLockSts_sig</PortName>
      </autosarInfo>
      <executionInterface type="ModelRefInfoRepo.InputExecutionInterface" uuid="6717b798-081e-4542-b0be-dbf162c42e21"/>
      <sigNameToEMVCEMap type="ModelRefInfoRepo.SigNameEMVCEInfo" uuid="93c072c3-46af-4d61-8d47-be1d58f4e1d0"/>
    </inports>
    <inports type="ModelRefInfoRepo.InportInformation" uuid="0cf1723f-9a92-4937-8755-fc056857722f">
      <isNotDerivPort>true</isNotDerivPort>
      <designMax>Inf</designMax>
      <designMin>-Inf</designMin>
      <indexType>2</indexType>
      <originalPortNumber>3</originalPortNumber>
      <rateInfos type="ModelRefInfoRepo.RateInfo">
        <compiled>true</compiled>
        <period>.01</period>
        <priority>41</priority>
        <rateIdx>1</rateIdx>
        <taskedExplicitly>true</taskedExplicitly>
      </rateInfos>
      <resolvedSignalObject></resolvedSignalObject>
      <autosarInfo type="ModelRefInfoRepo.AUTOSARInportInfo" uuid="69d20223-a744-4c0e-a6ab-8821c31800d9">
        <ElementName>VeOUT_SP_EspVehSpd_kmh</ElementName>
        <PortName>VeOUT_SP_EspVehSpd_kmh</PortName>
      </autosarInfo>
      <executionInterface type="ModelRefInfoRepo.InputExecutionInterface" uuid="59ffd5f2-7cbd-4193-a2f8-16caf7a5d04e"/>
      <sigNameToEMVCEMap type="ModelRefInfoRepo.SigNameEMVCEInfo" uuid="d02ad8a7-ec98-4b5a-8ab8-7dbe919c1b56"/>
    </inports>
    <inports type="ModelRefInfoRepo.InportInformation" uuid="182ccd42-4712-4f45-a887-0061ac4c3a4d">
      <isNotDerivPort>true</isNotDerivPort>
      <designMax>Inf</designMax>
      <designMin>-Inf</designMin>
      <indexType>2</indexType>
      <originalPortNumber>4</originalPortNumber>
      <rateInfos type="ModelRefInfoRepo.RateInfo">
        <compiled>true</compiled>
        <period>.01</period>
        <priority>41</priority>
        <rateIdx>1</rateIdx>
        <taskedExplicitly>true</taskedExplicitly>
      </rateInfos>
      <resolvedSignalObject></resolvedSignalObject>
      <autosarInfo type="ModelRefInfoRepo.AUTOSARInportInfo" uuid="9f474a5b-2234-4b07-8214-9346cf87fe92">
        <ElementName>VsINP_HWA_DriverHandleHall_sig</ElementName>
        <PortName>VsINP_HWA_DriverHandleHall_sig</PortName>
      </autosarInfo>
      <executionInterface type="ModelRefInfoRepo.InputExecutionInterface" uuid="bdbaaa2d-d8d2-4d28-845b-7c23accbaee3"/>
      <sigNameToEMVCEMap type="ModelRefInfoRepo.SigNameEMVCEInfo" uuid="7f497b4f-7586-4923-bda0-2faa0f08c1a1"/>
    </inports>
    <inports type="ModelRefInfoRepo.InportInformation" uuid="8d978ecf-4dd5-42a0-b6fa-8c898b32c22c">
      <isNotDerivPort>true</isNotDerivPort>
      <designMax>Inf</designMax>
      <designMin>-Inf</designMin>
      <indexType>2</indexType>
      <originalPortNumber>5</originalPortNumber>
      <rateInfos type="ModelRefInfoRepo.RateInfo">
        <compiled>true</compiled>
        <period>.01</period>
        <priority>41</priority>
        <rateIdx>1</rateIdx>
        <taskedExplicitly>true</taskedExplicitly>
      </rateInfos>
      <resolvedSignalObject></resolvedSignalObject>
      <autosarInfo type="ModelRefInfoRepo.AUTOSARInportInfo" uuid="ee490419-676b-4331-a087-bda587084c11">
        <ElementName>VsINP_HWA_RLHandleHall_sig</ElementName>
        <PortName>VsINP_HWA_RLHandleHall_sig</PortName>
      </autosarInfo>
      <executionInterface type="ModelRefInfoRepo.InputExecutionInterface" uuid="717125e8-4f74-43aa-902c-24a9a1b3d47b"/>
      <sigNameToEMVCEMap type="ModelRefInfoRepo.SigNameEMVCEInfo" uuid="84b2676a-4ead-454c-a634-2c6f55b17f80"/>
    </inports>
    <inports type="ModelRefInfoRepo.InportInformation" uuid="de59bd65-d873-484b-bee5-ae59dbb4e43e">
      <isNotDerivPort>true</isNotDerivPort>
      <designMax>Inf</designMax>
      <designMin>-Inf</designMin>
      <indexType>2</indexType>
      <originalPortNumber>6</originalPortNumber>
      <rateInfos type="ModelRefInfoRepo.RateInfo">
        <compiled>true</compiled>
        <period>.01</period>
        <priority>41</priority>
        <rateIdx>1</rateIdx>
        <taskedExplicitly>true</taskedExplicitly>
      </rateInfos>
      <resolvedSignalObject></resolvedSignalObject>
      <autosarInfo type="ModelRefInfoRepo.AUTOSARInportInfo" uuid="a896f1d8-7ec9-424c-a263-b92db1099e2d">
        <ElementName>VeINP_CAN_FRDoorHandleSts_sig</ElementName>
        <PortName>VeINP_CAN_FRDoorHandleSts_sig</PortName>
      </autosarInfo>
      <executionInterface type="ModelRefInfoRepo.InputExecutionInterface" uuid="43694808-d459-465c-a1fa-ec8be62d48ad"/>
      <sigNameToEMVCEMap type="ModelRefInfoRepo.SigNameEMVCEInfo" uuid="e104c800-0335-4c39-87ba-bfd079b19ff7"/>
    </inports>
    <inports type="ModelRefInfoRepo.InportInformation" uuid="6137439c-59b4-4204-941c-16edd3753a6d">
      <isNotDerivPort>true</isNotDerivPort>
      <designMax>Inf</designMax>
      <designMin>-Inf</designMin>
      <indexType>2</indexType>
      <originalPortNumber>7</originalPortNumber>
      <rateInfos type="ModelRefInfoRepo.RateInfo">
        <compiled>true</compiled>
        <period>.01</period>
        <priority>41</priority>
        <rateIdx>1</rateIdx>
        <taskedExplicitly>true</taskedExplicitly>
      </rateInfos>
      <resolvedSignalObject></resolvedSignalObject>
      <autosarInfo type="ModelRefInfoRepo.AUTOSARInportInfo" uuid="e810cad5-13aa-4803-aaf2-ddf7988c821c">
        <ElementName>VeINP_CAN_RRDoorHandleSts_sig</ElementName>
        <PortName>VeINP_CAN_RRDoorHandleSts_sig</PortName>
      </autosarInfo>
      <executionInterface type="ModelRefInfoRepo.InputExecutionInterface" uuid="59de697a-8b0a-4d72-a3cf-a1e5699f55f3"/>
      <sigNameToEMVCEMap type="ModelRefInfoRepo.SigNameEMVCEInfo" uuid="c56c0d89-74a7-4277-8084-48ac352faab4"/>
    </inports>
    <inports type="ModelRefInfoRepo.InportInformation" uuid="004d0da4-59e3-41ea-bfc0-a61cb0efbaec">
      <isNotDerivPort>true</isNotDerivPort>
      <designMax>Inf</designMax>
      <designMin>-Inf</designMin>
      <indexType>2</indexType>
      <originalPortNumber>8</originalPortNumber>
      <rateInfos type="ModelRefInfoRepo.RateInfo">
        <compiled>true</compiled>
        <period>.01</period>
        <priority>41</priority>
        <rateIdx>1</rateIdx>
        <taskedExplicitly>true</taskedExplicitly>
      </rateInfos>
      <resolvedSignalObject></resolvedSignalObject>
      <autosarInfo type="ModelRefInfoRepo.AUTOSARInportInfo" uuid="4f98aa76-dc1c-4819-b881-9a7848ab8716">
        <ElementName>VeOUT_SP_LHFdoorSts_sig</ElementName>
        <PortName>VeOUT_SP_LHFdoorSts_sig</PortName>
      </autosarInfo>
      <executionInterface type="ModelRefInfoRepo.InputExecutionInterface" uuid="3fd3116e-f99c-4e81-bca7-e382681a1366"/>
      <sigNameToEMVCEMap type="ModelRefInfoRepo.SigNameEMVCEInfo" uuid="5177330b-fd02-4d51-bd4f-dd7cc8631e61"/>
    </inports>
    <inports type="ModelRefInfoRepo.InportInformation" uuid="9a4198e0-ea68-4257-9ab3-055ff1566fd8">
      <isNotDerivPort>true</isNotDerivPort>
      <designMax>Inf</designMax>
      <designMin>-Inf</designMin>
      <indexType>2</indexType>
      <originalPortNumber>9</originalPortNumber>
      <rateInfos type="ModelRefInfoRepo.RateInfo">
        <compiled>true</compiled>
        <period>.01</period>
        <priority>41</priority>
        <rateIdx>1</rateIdx>
        <taskedExplicitly>true</taskedExplicitly>
      </rateInfos>
      <resolvedSignalObject></resolvedSignalObject>
      <autosarInfo type="ModelRefInfoRepo.AUTOSARInportInfo" uuid="ba4fc3ac-6887-4365-a699-60fc6b00e8b4">
        <ElementName>VeOUT_SP_LHRdoorSts_sig</ElementName>
        <PortName>VeOUT_SP_LHRdoorSts_sig</PortName>
      </autosarInfo>
      <executionInterface type="ModelRefInfoRepo.InputExecutionInterface" uuid="5da3b1b7-d6a1-470b-a52b-0930dac91f52"/>
      <sigNameToEMVCEMap type="ModelRefInfoRepo.SigNameEMVCEInfo" uuid="15df24f2-16f5-4fb5-ae13-ac22005e0532"/>
    </inports>
    <inports type="ModelRefInfoRepo.InportInformation" uuid="416e362e-8e1f-4b79-8935-499bb4bea86a">
      <isNotDerivPort>true</isNotDerivPort>
      <designMax>Inf</designMax>
      <designMin>-Inf</designMin>
      <indexType>2</indexType>
      <originalPortNumber>10</originalPortNumber>
      <rateInfos type="ModelRefInfoRepo.RateInfo">
        <compiled>true</compiled>
        <period>.01</period>
        <priority>41</priority>
        <rateIdx>1</rateIdx>
        <taskedExplicitly>true</taskedExplicitly>
      </rateInfos>
      <resolvedSignalObject></resolvedSignalObject>
      <autosarInfo type="ModelRefInfoRepo.AUTOSARInportInfo" uuid="cee3c9c0-ac7c-426a-8838-546a62c1a4a5">
        <ElementName>VeINP_CAN_RHFDoorSts_sig</ElementName>
        <PortName>VeINP_CAN_RHFDoorSts_sig</PortName>
      </autosarInfo>
      <executionInterface type="ModelRefInfoRepo.InputExecutionInterface" uuid="64f96393-dd58-43a1-be92-9168122868c9"/>
      <sigNameToEMVCEMap type="ModelRefInfoRepo.SigNameEMVCEInfo" uuid="cede98da-6ded-40d9-be16-497f4cc0fa23"/>
    </inports>
    <inports type="ModelRefInfoRepo.InportInformation" uuid="49441d51-a724-4d4f-88ca-7ceccedac005">
      <isNotDerivPort>true</isNotDerivPort>
      <designMax>Inf</designMax>
      <designMin>-Inf</designMin>
      <indexType>2</indexType>
      <originalPortNumber>11</originalPortNumber>
      <rateInfos type="ModelRefInfoRepo.RateInfo">
        <compiled>true</compiled>
        <period>.01</period>
        <priority>41</priority>
        <rateIdx>1</rateIdx>
        <taskedExplicitly>true</taskedExplicitly>
      </rateInfos>
      <resolvedSignalObject></resolvedSignalObject>
      <autosarInfo type="ModelRefInfoRepo.AUTOSARInportInfo" uuid="d74efd2b-89fd-450b-99cb-95624642d3f2">
        <ElementName>VeINP_CAN_RHRDoorSts_sig</ElementName>
        <PortName>VeINP_CAN_RHRDoorSts_sig</PortName>
      </autosarInfo>
      <executionInterface type="ModelRefInfoRepo.InputExecutionInterface" uuid="cbec56fa-eb18-4522-bca6-9b3d8eb4d070"/>
      <sigNameToEMVCEMap type="ModelRefInfoRepo.SigNameEMVCEInfo" uuid="0583d0bb-145a-461c-b6f0-de970fa4d3ba"/>
    </inports>
    <inports type="ModelRefInfoRepo.InportInformation" uuid="eceea2fb-afe4-495f-884b-afc38ab85858">
      <isNotDerivPort>true</isNotDerivPort>
      <designMax>Inf</designMax>
      <designMin>-Inf</designMin>
      <indexType>2</indexType>
      <originalPortNumber>12</originalPortNumber>
      <rateInfos type="ModelRefInfoRepo.RateInfo">
        <compiled>true</compiled>
        <period>.01</period>
        <priority>41</priority>
        <rateIdx>1</rateIdx>
        <taskedExplicitly>true</taskedExplicitly>
      </rateInfos>
      <resolvedSignalObject></resolvedSignalObject>
      <autosarInfo type="ModelRefInfoRepo.AUTOSARInportInfo" uuid="e52b9673-5cd7-4b8e-a1bd-77252a5d3e22">
        <ElementName>VbOUT_SP_CrashOutpSts_flg</ElementName>
        <PortName>VbOUT_SP_CrashOutpSts_flg</PortName>
      </autosarInfo>
      <executionInterface type="ModelRefInfoRepo.InputExecutionInterface" uuid="467400c4-5972-4cf8-a3d3-fb351f150c26"/>
      <sigNameToEMVCEMap type="ModelRefInfoRepo.SigNameEMVCEInfo" uuid="78db47d0-b242-4c60-a7be-fb86f09b1e29"/>
    </inports>
    <inports type="ModelRefInfoRepo.InportInformation" uuid="29b026cc-5d79-4f15-9128-f9133e527c33">
      <isNotDerivPort>true</isNotDerivPort>
      <designMax>Inf</designMax>
      <designMin>-Inf</designMin>
      <indexType>2</indexType>
      <originalPortNumber>13</originalPortNumber>
      <rateInfos type="ModelRefInfoRepo.RateInfo">
        <compiled>true</compiled>
        <period>.01</period>
        <priority>41</priority>
        <rateIdx>1</rateIdx>
        <taskedExplicitly>true</taskedExplicitly>
      </rateInfos>
      <resolvedSignalObject></resolvedSignalObject>
      <autosarInfo type="ModelRefInfoRepo.AUTOSARInportInfo" uuid="7e8c51b6-b272-4f00-a9f4-e238060cc16e">
        <ElementName>VsINP_EPRM_FLDoorHandleFromEE_sig</ElementName>
        <PortName>VsINP_EPRM_FLDoorHandleFromEE_sig</PortName>
      </autosarInfo>
      <executionInterface type="ModelRefInfoRepo.InputExecutionInterface" uuid="f22516f4-9c17-40cb-9a75-2ab265382de0"/>
      <sigNameToEMVCEMap type="ModelRefInfoRepo.SigNameEMVCEInfo" uuid="16003afd-03fa-472a-a1ed-8b6dd67c7b4c"/>
    </inports>
    <inports type="ModelRefInfoRepo.InportInformation" uuid="b32fe72b-baaf-4b02-99e4-b6b921b5953c">
      <isNotDerivPort>true</isNotDerivPort>
      <designMax>Inf</designMax>
      <designMin>-Inf</designMin>
      <indexType>2</indexType>
      <originalPortNumber>14</originalPortNumber>
      <rateInfos type="ModelRefInfoRepo.RateInfo">
        <compiled>true</compiled>
        <period>.01</period>
        <priority>41</priority>
        <rateIdx>1</rateIdx>
        <taskedExplicitly>true</taskedExplicitly>
      </rateInfos>
      <resolvedSignalObject></resolvedSignalObject>
      <autosarInfo type="ModelRefInfoRepo.AUTOSARInportInfo" uuid="be18b938-be2f-4208-bde9-e48e38fbb2dc">
        <ElementName>VsINP_EPRM_RLDoorHandleFromEE_sig</ElementName>
        <PortName>VsINP_EPRM_RLDoorHandleFromEE_sig</PortName>
      </autosarInfo>
      <executionInterface type="ModelRefInfoRepo.InputExecutionInterface" uuid="4aa2caaa-cbcd-4e1d-a8c7-d4b08b85fd1f"/>
      <sigNameToEMVCEMap type="ModelRefInfoRepo.SigNameEMVCEInfo" uuid="57b13fa5-124e-4a60-8cae-0e17029232b6"/>
    </inports>
    <inports type="ModelRefInfoRepo.InportInformation" uuid="6ee99227-09fd-47f7-95b0-056d09a3bab8">
      <isNotDerivPort>true</isNotDerivPort>
      <designMax>Inf</designMax>
      <designMin>-Inf</designMin>
      <indexType>2</indexType>
      <originalPortNumber>15</originalPortNumber>
      <rateInfos type="ModelRefInfoRepo.RateInfo">
        <compiled>true</compiled>
        <period>.01</period>
        <priority>41</priority>
        <rateIdx>1</rateIdx>
        <taskedExplicitly>true</taskedExplicitly>
      </rateInfos>
      <resolvedSignalObject></resolvedSignalObject>
      <autosarInfo type="ModelRefInfoRepo.AUTOSARInportInfo" uuid="1edde574-8631-43fd-ba6e-3833d3533a89">
        <ElementName>VeINP_EPRM_FLDoorHandleLrnStsEE_sig</ElementName>
        <PortName>VeINP_EPRM_FLDoorHandleLrnStsEE_sig</PortName>
      </autosarInfo>
      <executionInterface type="ModelRefInfoRepo.InputExecutionInterface" uuid="eab4b907-5a9c-477c-bf60-6543d29ad99c"/>
      <sigNameToEMVCEMap type="ModelRefInfoRepo.SigNameEMVCEInfo" uuid="d98a883f-73a0-4dbd-a099-22967f7196e7"/>
    </inports>
    <inports type="ModelRefInfoRepo.InportInformation" uuid="11b7e0cb-5706-466e-9cdd-0d351fa1a358">
      <isNotDerivPort>true</isNotDerivPort>
      <designMax>Inf</designMax>
      <designMin>-Inf</designMin>
      <indexType>2</indexType>
      <originalPortNumber>16</originalPortNumber>
      <rateInfos type="ModelRefInfoRepo.RateInfo">
        <compiled>true</compiled>
        <period>.01</period>
        <priority>41</priority>
        <rateIdx>1</rateIdx>
        <taskedExplicitly>true</taskedExplicitly>
      </rateInfos>
      <resolvedSignalObject></resolvedSignalObject>
      <autosarInfo type="ModelRefInfoRepo.AUTOSARInportInfo" uuid="2651b1ce-113b-4af6-9a99-e3388a59ab7d">
        <ElementName>VeINP_EPRM_RLDoorHandleLrnStsEE_sig</ElementName>
        <PortName>VeINP_EPRM_RLDoorHandleLrnStsEE_sig</PortName>
      </autosarInfo>
      <executionInterface type="ModelRefInfoRepo.InputExecutionInterface" uuid="006e212e-7c0e-4a00-ab48-e9e64133f51d"/>
      <sigNameToEMVCEMap type="ModelRefInfoRepo.SigNameEMVCEInfo" uuid="c34c7b87-8cc9-4b1d-828d-9c814907c1ee"/>
    </inports>
    <inports type="ModelRefInfoRepo.InportInformation" uuid="85ad685e-13c0-46df-8c42-ae250c17a286">
      <isNotDerivPort>true</isNotDerivPort>
      <designMax>Inf</designMax>
      <designMin>-Inf</designMin>
      <indexType>2</indexType>
      <originalPortNumber>17</originalPortNumber>
      <rateInfos type="ModelRefInfoRepo.RateInfo">
        <compiled>true</compiled>
        <period>.01</period>
        <priority>41</priority>
        <rateIdx>1</rateIdx>
        <taskedExplicitly>true</taskedExplicitly>
      </rateInfos>
      <resolvedSignalObject></resolvedSignalObject>
      <autosarInfo type="ModelRefInfoRepo.AUTOSARInportInfo" uuid="a323bc01-4877-40a6-ae40-99aa7229b592">
        <ElementName>VeINP_CAN_FRDoorHandleLrnSts_sig</ElementName>
        <PortName>VeINP_CAN_FRDoorHandleLrnSts_sig</PortName>
      </autosarInfo>
      <executionInterface type="ModelRefInfoRepo.InputExecutionInterface" uuid="f79a8c24-0db5-43b0-942a-af9535fe59f3"/>
      <sigNameToEMVCEMap type="ModelRefInfoRepo.SigNameEMVCEInfo" uuid="0e489136-d6c8-4a5b-8cec-d64b162f1517"/>
    </inports>
    <inports type="ModelRefInfoRepo.InportInformation" uuid="5c15abe1-f238-49b3-afa1-c2c32400a3d1">
      <isNotDerivPort>true</isNotDerivPort>
      <designMax>Inf</designMax>
      <designMin>-Inf</designMin>
      <indexType>2</indexType>
      <originalPortNumber>18</originalPortNumber>
      <rateInfos type="ModelRefInfoRepo.RateInfo">
        <compiled>true</compiled>
        <period>.01</period>
        <priority>41</priority>
        <rateIdx>1</rateIdx>
        <taskedExplicitly>true</taskedExplicitly>
      </rateInfos>
      <resolvedSignalObject></resolvedSignalObject>
      <autosarInfo type="ModelRefInfoRepo.AUTOSARInportInfo" uuid="68619344-f846-4cdf-92ff-83ef695a7c46">
        <ElementName>VeINP_CAN_RRDoorHandleLrnSts_sig</ElementName>
        <PortName>VeINP_CAN_RRDoorHandleLrnSts_sig</PortName>
      </autosarInfo>
      <executionInterface type="ModelRefInfoRepo.InputExecutionInterface" uuid="e6823c1d-e4a7-4ec7-9b04-f18f8de214ef"/>
      <sigNameToEMVCEMap type="ModelRefInfoRepo.SigNameEMVCEInfo" uuid="21d4015a-bf70-4db2-992a-0163a532b04f"/>
    </inports>
    <inports type="ModelRefInfoRepo.InportInformation" uuid="be4dd467-d306-4710-9ec1-279e6ad80b08">
      <isNotDerivPort>true</isNotDerivPort>
      <designMax>Inf</designMax>
      <designMin>-Inf</designMin>
      <indexType>2</indexType>
      <originalPortNumber>19</originalPortNumber>
      <rateInfos type="ModelRefInfoRepo.RateInfo">
        <compiled>true</compiled>
        <period>.01</period>
        <priority>41</priority>
        <rateIdx>1</rateIdx>
        <taskedExplicitly>true</taskedExplicitly>
      </rateInfos>
      <resolvedSignalObject></resolvedSignalObject>
      <autosarInfo type="ModelRefInfoRepo.AUTOSARInportInfo" uuid="aa3e92fd-6369-4b0b-b44a-82a2ce8e67ca">
        <ElementName>VbINP_HWA_DoorHandleLrnReq_flg</ElementName>
        <PortName>VbINP_HWA_DoorHandleLrnReq_flg</PortName>
      </autosarInfo>
      <executionInterface type="ModelRefInfoRepo.InputExecutionInterface" uuid="28b01fc5-4073-4c1d-98b0-6aa48e34fbd3"/>
      <sigNameToEMVCEMap type="ModelRefInfoRepo.SigNameEMVCEInfo" uuid="148fd4ba-12b9-490c-999d-4d0c74a06284"/>
    </inports>
    <isBdInSimModeForSimCodegenVariants>false</isBdInSimModeForSimCodegenVariants>
    <isInlineParamsOn>true</isInlineParamsOn>
    <isNumAllowedInstancesOne>true</isNumAllowedInstancesOne>
    <isOrigInportVirtualBus>false</isOrigInportVirtualBus>
    <isOrigInportVirtualBus>false</isOrigInportVirtualBus>
    <isOrigInportVirtualBus>false</isOrigInportVirtualBus>
    <isOrigInportVirtualBus>false</isOrigInportVirtualBus>
    <isOrigInportVirtualBus>false</isOrigInportVirtualBus>
    <isOrigInportVirtualBus>false</isOrigInportVirtualBus>
    <isOrigInportVirtualBus>false</isOrigInportVirtualBus>
    <isOrigInportVirtualBus>false</isOrigInportVirtualBus>
    <isOrigInportVirtualBus>false</isOrigInportVirtualBus>
    <isOrigInportVirtualBus>false</isOrigInportVirtualBus>
    <isOrigInportVirtualBus>false</isOrigInportVirtualBus>
    <isOrigInportVirtualBus>false</isOrigInportVirtualBus>
    <isOrigInportVirtualBus>false</isOrigInportVirtualBus>
    <isOrigInportVirtualBus>false</isOrigInportVirtualBus>
    <isOrigInportVirtualBus>false</isOrigInportVirtualBus>
    <isOrigInportVirtualBus>false</isOrigInportVirtualBus>
    <isOrigInportVirtualBus>false</isOrigInportVirtualBus>
    <isOrigInportVirtualBus>false</isOrigInportVirtualBus>
    <isOrigInportVirtualBus>false</isOrigInportVirtualBus>
    <isOrigInportVirtualBus>false</isOrigInportVirtualBus>
    <isOrigOutportVirtualBus>false</isOrigOutportVirtualBus>
    <isOrigOutportVirtualBus>false</isOrigOutportVirtualBus>
    <isOrigOutportVirtualBus>false</isOrigOutportVirtualBus>
    <isOrigOutportVirtualBus>false</isOrigOutportVirtualBus>
    <isOrigOutportVirtualBus>false</isOrigOutportVirtualBus>
    <isOrigOutportVirtualBus>false</isOrigOutportVirtualBus>
    <isOrigOutportVirtualBus>false</isOrigOutportVirtualBus>
    <isOrigOutportVirtualBus>false</isOrigOutportVirtualBus>
    <isOrigOutportVirtualBus>false</isOrigOutportVirtualBus>
    <isOrigOutportVirtualBus>false</isOrigOutportVirtualBus>
    <isOrigOutportVirtualBus>false</isOrigOutportVirtualBus>
    <isOrigOutportVirtualBus>false</isOrigOutportVirtualBus>
    <isOrigOutportVirtualBus>false</isOrigOutportVirtualBus>
    <isOrigOutportVirtualBus>false</isOrigOutportVirtualBus>
    <isOrigOutportVirtualBus>false</isOrigOutportVirtualBus>
    <isOrigOutportVirtualBus>false</isOrigOutportVirtualBus>
    <loggingSaveFormat>6</loggingSaveFormat>
    <maxFreqHz>-1.0</maxFreqHz>
    <numDStateRecs>8</numDStateRecs>
    <numDataInputPorts>20</numDataInputPorts>
    <numInportFcnCallPortGroups>1</numInportFcnCallPortGroups>
    <numLoggableDStateRecs>8</numLoggableDStateRecs>
    <numLoggableJacobianDStates>0</numLoggableJacobianDStates>
    <origInportBusType></origInportBusType>
    <origInportBusType></origInportBusType>
    <origInportBusType></origInportBusType>
    <origInportBusType></origInportBusType>
    <origInportBusType></origInportBusType>
    <origInportBusType></origInportBusType>
    <origInportBusType></origInportBusType>
    <origInportBusType></origInportBusType>
    <origInportBusType></origInportBusType>
    <origInportBusType></origInportBusType>
    <origInportBusType></origInportBusType>
    <origInportBusType></origInportBusType>
    <origInportBusType></origInportBusType>
    <origInportBusType></origInportBusType>
    <origInportBusType></origInportBusType>
    <origInportBusType></origInportBusType>
    <origInportBusType></origInportBusType>
    <origInportBusType></origInportBusType>
    <origInportBusType></origInportBusType>
    <origInportBusType></origInportBusType>
    <origOutportBusOutputAsStruct>false</origOutportBusOutputAsStruct>
    <origOutportBusOutputAsStruct>false</origOutportBusOutputAsStruct>
    <origOutportBusOutputAsStruct>false</origOutportBusOutputAsStruct>
    <origOutportBusOutputAsStruct>false</origOutportBusOutputAsStruct>
    <origOutportBusOutputAsStruct>false</origOutportBusOutputAsStruct>
    <origOutportBusOutputAsStruct>false</origOutportBusOutputAsStruct>
    <origOutportBusOutputAsStruct>false</origOutportBusOutputAsStruct>
    <origOutportBusOutputAsStruct>false</origOutportBusOutputAsStruct>
    <origOutportBusOutputAsStruct>false</origOutportBusOutputAsStruct>
    <origOutportBusOutputAsStruct>false</origOutportBusOutputAsStruct>
    <origOutportBusOutputAsStruct>false</origOutportBusOutputAsStruct>
    <origOutportBusOutputAsStruct>false</origOutportBusOutputAsStruct>
    <origOutportBusOutputAsStruct>false</origOutportBusOutputAsStruct>
    <origOutportBusOutputAsStruct>false</origOutportBusOutputAsStruct>
    <origOutportBusOutputAsStruct>false</origOutportBusOutputAsStruct>
    <origOutportBusOutputAsStruct>false</origOutportBusOutputAsStruct>
    <origOutportBusType></origOutportBusType>
    <origOutportBusType></origOutportBusType>
    <origOutportBusType></origOutportBusType>
    <origOutportBusType></origOutportBusType>
    <origOutportBusType></origOutportBusType>
    <origOutportBusType></origOutportBusType>
    <origOutportBusType></origOutportBusType>
    <origOutportBusType></origOutportBusType>
    <origOutportBusType></origOutportBusType>
    <origOutportBusType></origOutportBusType>
    <origOutportBusType></origOutportBusType>
    <origOutportBusType></origOutportBusType>
    <origOutportBusType></origOutportBusType>
    <origOutportBusType></origOutportBusType>
    <origOutportBusType></origOutportBusType>
    <origOutportBusType></origOutportBusType>
    <outports type="ModelRefInfoRepo.OutportInformation" uuid="0fd160e5-7ebe-4cd3-a631-c7b493ce67a9">
      <hasSystemInitMethod>true</hasSystemInitMethod>
      <isInitializedWithIC>true</isInitializedWithIC>
      <designMax>Inf</designMax>
      <designMin>-Inf</designMin>
      <rateInfos type="ModelRefInfoRepo.RateInfo">
        <compiled>true</compiled>
        <period>.01</period>
        <priority>41</priority>
        <rateIdx>1</rateIdx>
        <taskedExplicitly>true</taskedExplicitly>
      </rateInfos>
      <resolvedSignalObject></resolvedSignalObject>
      <autosarInfo type="ModelRefInfoRepo.AUTOSAROutportInfo" uuid="4b0c8f90-5bab-4416-8126-f6c248d14181">
        <ElementName>VeOUT_DHM_FLHandleFoldedStatus_sig</ElementName>
        <PortName>VeOUT_DHM_FLHandleFoldedStatus_sig</PortName>
      </autosarInfo>
      <executionInterface type="ModelRefInfoRepo.OutputExecutionInterface" uuid="310bc969-aa15-491c-b254-284455764474"/>
      <sigNameToEMVCEMap type="ModelRefInfoRepo.SigNameEMVCEInfo" uuid="689a3cac-0fd9-4c76-9006-d67619ef1dc0"/>
    </outports>
    <outports type="ModelRefInfoRepo.OutportInformation" uuid="f2b05fd4-5a15-4799-87cc-5be057b78f40">
      <hasSystemInitMethod>true</hasSystemInitMethod>
      <isInitializedWithIC>true</isInitializedWithIC>
      <designMax>Inf</designMax>
      <designMin>-Inf</designMin>
      <originalPortNumber>1</originalPortNumber>
      <rateInfos type="ModelRefInfoRepo.RateInfo">
        <compiled>true</compiled>
        <period>.01</period>
        <priority>41</priority>
        <rateIdx>1</rateIdx>
        <taskedExplicitly>true</taskedExplicitly>
      </rateInfos>
      <resolvedSignalObject></resolvedSignalObject>
      <autosarInfo type="ModelRefInfoRepo.AUTOSAROutportInfo" uuid="363b9706-5e14-4ea6-8e48-b05a3947c58c">
        <ElementName>VeOUT_DHM_RLHandleFoldedStatus_sig</ElementName>
        <PortName>VeOUT_DHM_RLHandleFoldedStatus_sig</PortName>
      </autosarInfo>
      <executionInterface type="ModelRefInfoRepo.OutputExecutionInterface" uuid="8f784ba1-a0da-49e2-ac2b-eeeec63cccf6"/>
      <sigNameToEMVCEMap type="ModelRefInfoRepo.SigNameEMVCEInfo" uuid="560f6c4b-9f69-48b4-98f4-3571b69e0d2a"/>
    </outports>
    <outports type="ModelRefInfoRepo.OutportInformation" uuid="754a82d0-38ef-4932-93f8-97b3b5ec2adb">
      <hasSystemInitMethod>true</hasSystemInitMethod>
      <isInitializedWithIC>true</isInitializedWithIC>
      <designMax>Inf</designMax>
      <designMin>-Inf</designMin>
      <originalPortNumber>2</originalPortNumber>
      <rateInfos type="ModelRefInfoRepo.RateInfo">
        <compiled>true</compiled>
        <period>.01</period>
        <priority>41</priority>
        <rateIdx>1</rateIdx>
        <taskedExplicitly>true</taskedExplicitly>
      </rateInfos>
      <resolvedSignalObject></resolvedSignalObject>
      <autosarInfo type="ModelRefInfoRepo.AUTOSAROutportInfo" uuid="b36c9b60-be0d-4252-b76b-0ef4d8125988">
        <ElementName>VeOUT_DHM_FRHandleFoldedStatus_sig</ElementName>
        <PortName>VeOUT_DHM_FRHandleFoldedStatus_sig</PortName>
      </autosarInfo>
      <executionInterface type="ModelRefInfoRepo.OutputExecutionInterface" uuid="535faffc-8c8e-40d6-9fc4-01dcc1905237"/>
      <sigNameToEMVCEMap type="ModelRefInfoRepo.SigNameEMVCEInfo" uuid="074c66dc-4cd4-421e-be4e-0a4e7624a1a5"/>
    </outports>
    <outports type="ModelRefInfoRepo.OutportInformation" uuid="c2a4cb4c-2ef5-46fa-91ee-d9a34c062e43">
      <hasSystemInitMethod>true</hasSystemInitMethod>
      <isInitializedWithIC>true</isInitializedWithIC>
      <designMax>Inf</designMax>
      <designMin>-Inf</designMin>
      <originalPortNumber>3</originalPortNumber>
      <rateInfos type="ModelRefInfoRepo.RateInfo">
        <compiled>true</compiled>
        <period>.01</period>
        <priority>41</priority>
        <rateIdx>1</rateIdx>
        <taskedExplicitly>true</taskedExplicitly>
      </rateInfos>
      <resolvedSignalObject></resolvedSignalObject>
      <autosarInfo type="ModelRefInfoRepo.AUTOSAROutportInfo" uuid="60b7a00b-e95c-4c4f-b8bf-f2aad1acd58c">
        <ElementName>VeOUT_DHM_RRHandleFoldedStatus_sig</ElementName>
        <PortName>VeOUT_DHM_RRHandleFoldedStatus_sig</PortName>
      </autosarInfo>
      <executionInterface type="ModelRefInfoRepo.OutputExecutionInterface" uuid="83f846a3-8b2a-4d79-83a1-8a9de990a85a"/>
      <sigNameToEMVCEMap type="ModelRefInfoRepo.SigNameEMVCEInfo" uuid="fada2f0f-db3f-44c9-b85d-139c72f3309e"/>
    </outports>
    <outports type="ModelRefInfoRepo.OutportInformation" uuid="276aeb0e-2cc8-49bb-ac7d-5cd83af1ba89">
      <drivenByOutputPortWithCGInit>true</drivenByOutputPortWithCGInit>
      <hasSystemInitMethod>true</hasSystemInitMethod>
      <isInitializedWithIC>true</isInitializedWithIC>
      <designMax>Inf</designMax>
      <designMin>-Inf</designMin>
      <originalPortNumber>4</originalPortNumber>
      <rateInfos type="ModelRefInfoRepo.RateInfo">
        <compiled>true</compiled>
        <period>.01</period>
        <priority>41</priority>
        <rateIdx>1</rateIdx>
        <taskedExplicitly>true</taskedExplicitly>
      </rateInfos>
      <resolvedSignalObject></resolvedSignalObject>
      <autosarInfo type="ModelRefInfoRepo.AUTOSAROutportInfo" uuid="3cd1f55a-a0e8-4880-b282-a184acf91f6f">
        <ElementName>VeOUT_DHM_FRDoorHandleReq_sig</ElementName>
        <PortName>VeOUT_DHM_FRDoorHandleReq_sig</PortName>
      </autosarInfo>
      <executionInterface type="ModelRefInfoRepo.OutputExecutionInterface" uuid="8f36153c-4c62-45c1-b9c7-b17226b3d4f3"/>
      <sigNameToEMVCEMap type="ModelRefInfoRepo.SigNameEMVCEInfo" uuid="55a2cbfd-b1cc-4b08-b7d9-2d4150cd4e47"/>
    </outports>
    <outports type="ModelRefInfoRepo.OutportInformation" uuid="7f3c34bc-661a-4b1e-9a4f-b5e3b7393270">
      <drivenByOutputPortWithCGInit>true</drivenByOutputPortWithCGInit>
      <hasSystemInitMethod>true</hasSystemInitMethod>
      <isInitializedWithIC>true</isInitializedWithIC>
      <designMax>Inf</designMax>
      <designMin>-Inf</designMin>
      <originalPortNumber>5</originalPortNumber>
      <rateInfos type="ModelRefInfoRepo.RateInfo">
        <compiled>true</compiled>
        <period>.01</period>
        <priority>41</priority>
        <rateIdx>1</rateIdx>
        <taskedExplicitly>true</taskedExplicitly>
      </rateInfos>
      <resolvedSignalObject></resolvedSignalObject>
      <autosarInfo type="ModelRefInfoRepo.AUTOSAROutportInfo" uuid="824174ed-43e3-4cc9-b5d8-50a4316fddb5">
        <ElementName>VeOUT_DHM_RRDoorHandleReq_sig</ElementName>
        <PortName>VeOUT_DHM_RRDoorHandleReq_sig</PortName>
      </autosarInfo>
      <executionInterface type="ModelRefInfoRepo.OutputExecutionInterface" uuid="c1ff03fb-1c1c-47c7-b9b3-846246f7cfe4"/>
      <sigNameToEMVCEMap type="ModelRefInfoRepo.SigNameEMVCEInfo" uuid="e27bedf9-97a6-409c-9180-4b0cb26d17c2"/>
    </outports>
    <outports type="ModelRefInfoRepo.OutportInformation" uuid="66e718ba-c1a9-49fc-844e-980944fc2a2b">
      <drivenByOutputPortWithCGInit>true</drivenByOutputPortWithCGInit>
      <hasSystemInitMethod>true</hasSystemInitMethod>
      <isInitializedWithIC>true</isInitializedWithIC>
      <designMax>Inf</designMax>
      <designMin>-Inf</designMin>
      <originalPortNumber>6</originalPortNumber>
      <rateInfos type="ModelRefInfoRepo.RateInfo">
        <compiled>true</compiled>
        <period>.01</period>
        <priority>41</priority>
        <rateIdx>1</rateIdx>
        <taskedExplicitly>true</taskedExplicitly>
      </rateInfos>
      <resolvedSignalObject></resolvedSignalObject>
      <autosarInfo type="ModelRefInfoRepo.AUTOSAROutportInfo" uuid="b525f160-d9b0-4f17-88d2-a5fa32726fe3">
        <ElementName>VbOUT_DHM_FLHadUnfold_flg</ElementName>
        <PortName>VbOUT_DHM_FLHadUnfold_flg</PortName>
      </autosarInfo>
      <executionInterface type="ModelRefInfoRepo.OutputExecutionInterface" uuid="94a74ae8-3af2-4757-b57e-f73d58d7f81c"/>
      <sigNameToEMVCEMap type="ModelRefInfoRepo.SigNameEMVCEInfo" uuid="a5354533-fb6a-4ace-b762-42a410230e7a"/>
    </outports>
    <outports type="ModelRefInfoRepo.OutportInformation" uuid="38308da5-df4c-4d3a-8cb0-a69021b4a8da">
      <drivenByOutputPortWithCGInit>true</drivenByOutputPortWithCGInit>
      <hasSystemInitMethod>true</hasSystemInitMethod>
      <isInitializedWithIC>true</isInitializedWithIC>
      <designMax>Inf</designMax>
      <designMin>-Inf</designMin>
      <originalPortNumber>7</originalPortNumber>
      <rateInfos type="ModelRefInfoRepo.RateInfo">
        <compiled>true</compiled>
        <period>.01</period>
        <priority>41</priority>
        <rateIdx>1</rateIdx>
        <taskedExplicitly>true</taskedExplicitly>
      </rateInfos>
      <resolvedSignalObject></resolvedSignalObject>
      <autosarInfo type="ModelRefInfoRepo.AUTOSAROutportInfo" uuid="ba055cb5-14cc-41fa-8a24-3b41a62701c4">
        <ElementName>VbOUT_DHM_FLHadFold_flg</ElementName>
        <PortName>VbOUT_DHM_FLHadFold_flg</PortName>
      </autosarInfo>
      <executionInterface type="ModelRefInfoRepo.OutputExecutionInterface" uuid="71be7013-28e1-4d03-bc1d-4d1702ed9046"/>
      <sigNameToEMVCEMap type="ModelRefInfoRepo.SigNameEMVCEInfo" uuid="43d7cb6e-7732-49a2-a601-6906173dadd3"/>
    </outports>
    <outports type="ModelRefInfoRepo.OutportInformation" uuid="3ae8d5ca-df12-4ea9-bcce-b06e3b85601e">
      <drivenByOutputPortWithCGInit>true</drivenByOutputPortWithCGInit>
      <hasSystemInitMethod>true</hasSystemInitMethod>
      <isInitializedWithIC>true</isInitializedWithIC>
      <designMax>Inf</designMax>
      <designMin>-Inf</designMin>
      <originalPortNumber>8</originalPortNumber>
      <rateInfos type="ModelRefInfoRepo.RateInfo">
        <compiled>true</compiled>
        <period>.01</period>
        <priority>41</priority>
        <rateIdx>1</rateIdx>
        <taskedExplicitly>true</taskedExplicitly>
      </rateInfos>
      <resolvedSignalObject></resolvedSignalObject>
      <autosarInfo type="ModelRefInfoRepo.AUTOSAROutportInfo" uuid="713ffbad-8fa4-47da-a292-69ad8885ba99">
        <ElementName>VbOUT_DHM_RLHandleUnfold_flg</ElementName>
        <PortName>VbOUT_DHM_RLHandleUnfold_flg</PortName>
      </autosarInfo>
      <executionInterface type="ModelRefInfoRepo.OutputExecutionInterface" uuid="435039eb-bf37-413d-90d2-ae77308684a3"/>
      <sigNameToEMVCEMap type="ModelRefInfoRepo.SigNameEMVCEInfo" uuid="d060de32-ae10-47af-a6d3-dc903002d5b7"/>
    </outports>
    <outports type="ModelRefInfoRepo.OutportInformation" uuid="7ac40cc2-b372-403c-8559-eb3ab9211b2e">
      <drivenByOutputPortWithCGInit>true</drivenByOutputPortWithCGInit>
      <hasSystemInitMethod>true</hasSystemInitMethod>
      <isInitializedWithIC>true</isInitializedWithIC>
      <designMax>Inf</designMax>
      <designMin>-Inf</designMin>
      <originalPortNumber>9</originalPortNumber>
      <rateInfos type="ModelRefInfoRepo.RateInfo">
        <compiled>true</compiled>
        <period>.01</period>
        <priority>41</priority>
        <rateIdx>1</rateIdx>
        <taskedExplicitly>true</taskedExplicitly>
      </rateInfos>
      <resolvedSignalObject></resolvedSignalObject>
      <autosarInfo type="ModelRefInfoRepo.AUTOSAROutportInfo" uuid="b19e2586-8aa0-4600-840a-ee344183b558">
        <ElementName>VbOUT_DHM_RLHandleFold_flg</ElementName>
        <PortName>VbOUT_DHM_RLHandleFold_flg</PortName>
      </autosarInfo>
      <executionInterface type="ModelRefInfoRepo.OutputExecutionInterface" uuid="d14a97e6-ffb6-42a3-bbb2-e8439f05c682"/>
      <sigNameToEMVCEMap type="ModelRefInfoRepo.SigNameEMVCEInfo" uuid="debb4cce-4c7b-43f2-a45c-9567898f46f3"/>
    </outports>
    <outports type="ModelRefInfoRepo.OutportInformation" uuid="e3d3281e-e000-44f2-b5bb-6acd8d7ca62f">
      <drivenByOutputPortWithCGInit>true</drivenByOutputPortWithCGInit>
      <hasSystemInitMethod>true</hasSystemInitMethod>
      <isInitializedWithIC>true</isInitializedWithIC>
      <designMax>Inf</designMax>
      <designMin>-Inf</designMin>
      <originalPortNumber>10</originalPortNumber>
      <rateInfos type="ModelRefInfoRepo.RateInfo">
        <compiled>true</compiled>
        <period>.01</period>
        <priority>41</priority>
        <rateIdx>1</rateIdx>
        <taskedExplicitly>true</taskedExplicitly>
      </rateInfos>
      <resolvedSignalObject></resolvedSignalObject>
      <autosarInfo type="ModelRefInfoRepo.AUTOSAROutportInfo" uuid="3bbfce4e-0388-434d-81a5-6fbd4a57e17c">
        <ElementName>VsINP_DHM_FLDoorHandleEE_sig</ElementName>
        <PortName>VsINP_DHM_FLDoorHandleEE_sig</PortName>
      </autosarInfo>
      <executionInterface type="ModelRefInfoRepo.OutputExecutionInterface" uuid="22060f9f-010e-4488-8d19-4eb71337c741"/>
      <sigNameToEMVCEMap type="ModelRefInfoRepo.SigNameEMVCEInfo" uuid="32c771ce-2cd8-4c85-853a-3ac163914bd8"/>
    </outports>
    <outports type="ModelRefInfoRepo.OutportInformation" uuid="1146ba15-aa54-4341-88f0-82d27914a005">
      <drivenByOutputPortWithCGInit>true</drivenByOutputPortWithCGInit>
      <hasSystemInitMethod>true</hasSystemInitMethod>
      <isInitializedWithIC>true</isInitializedWithIC>
      <designMax>Inf</designMax>
      <designMin>-Inf</designMin>
      <originalPortNumber>11</originalPortNumber>
      <rateInfos type="ModelRefInfoRepo.RateInfo">
        <compiled>true</compiled>
        <period>.01</period>
        <priority>41</priority>
        <rateIdx>1</rateIdx>
        <taskedExplicitly>true</taskedExplicitly>
      </rateInfos>
      <resolvedSignalObject></resolvedSignalObject>
      <autosarInfo type="ModelRefInfoRepo.AUTOSAROutportInfo" uuid="1240836f-0782-404a-ba13-64192f2dd84f">
        <ElementName>VsINP_DHM_RLDoorHandleEE_sig</ElementName>
        <PortName>VsINP_DHM_RLDoorHandleEE_sig</PortName>
      </autosarInfo>
      <executionInterface type="ModelRefInfoRepo.OutputExecutionInterface" uuid="851e87cb-b45c-4709-86be-f337afd6c88c"/>
      <sigNameToEMVCEMap type="ModelRefInfoRepo.SigNameEMVCEInfo" uuid="2ecb3278-24a1-422d-8bb0-629d37a71901"/>
    </outports>
    <outports type="ModelRefInfoRepo.OutportInformation" uuid="75861286-84ac-4fe3-830a-b10ac76fbede">
      <drivenByOutputPortWithCGInit>true</drivenByOutputPortWithCGInit>
      <hasSystemInitMethod>true</hasSystemInitMethod>
      <isInitializedWithIC>true</isInitializedWithIC>
      <designMax>Inf</designMax>
      <designMin>-Inf</designMin>
      <originalPortNumber>12</originalPortNumber>
      <rateInfos type="ModelRefInfoRepo.RateInfo">
        <compiled>true</compiled>
        <period>.01</period>
        <priority>41</priority>
        <rateIdx>1</rateIdx>
        <taskedExplicitly>true</taskedExplicitly>
      </rateInfos>
      <resolvedSignalObject></resolvedSignalObject>
      <autosarInfo type="ModelRefInfoRepo.AUTOSAROutportInfo" uuid="ceb42afb-6eed-4ebf-b10c-6092942d69f4">
        <ElementName>VeOUT_DHM_DoorHandleLrnSts_sig</ElementName>
        <PortName>VeOUT_DHM_DoorHandleLrnSts_sig</PortName>
      </autosarInfo>
      <executionInterface type="ModelRefInfoRepo.OutputExecutionInterface" uuid="7d186ab9-3d72-4280-8893-c61d73a2b2af"/>
      <sigNameToEMVCEMap type="ModelRefInfoRepo.SigNameEMVCEInfo" uuid="83743cbb-941d-4c92-87fe-3e2d9518064f"/>
    </outports>
    <outports type="ModelRefInfoRepo.OutportInformation" uuid="d9005dbe-db0a-4cdd-9804-85de8fe62d2c">
      <hasSystemInitMethod>true</hasSystemInitMethod>
      <isInitializedWithIC>true</isInitializedWithIC>
      <designMax>Inf</designMax>
      <designMin>-Inf</designMin>
      <originalPortNumber>13</originalPortNumber>
      <rateInfos type="ModelRefInfoRepo.RateInfo">
        <compiled>true</compiled>
        <period>.01</period>
        <priority>41</priority>
        <rateIdx>1</rateIdx>
        <taskedExplicitly>true</taskedExplicitly>
      </rateInfos>
      <resolvedSignalObject></resolvedSignalObject>
      <autosarInfo type="ModelRefInfoRepo.AUTOSAROutportInfo" uuid="8e8a1727-7522-4688-957c-3e18f99cc854">
        <ElementName>VeOUT_DHM_FLDoorHandleLrnStsEE_sig</ElementName>
        <PortName>VeOUT_DHM_FLDoorHandleLrnStsEE_sig</PortName>
      </autosarInfo>
      <executionInterface type="ModelRefInfoRepo.OutputExecutionInterface" uuid="7e851d7c-8098-4fa0-a78d-eea7df3d78d0"/>
      <sigNameToEMVCEMap type="ModelRefInfoRepo.SigNameEMVCEInfo" uuid="b3892f5c-5757-467f-b939-ad6c208af501"/>
    </outports>
    <outports type="ModelRefInfoRepo.OutportInformation" uuid="34a05a2d-37c3-43f0-9555-414c4dd4ec2c">
      <hasSystemInitMethod>true</hasSystemInitMethod>
      <isInitializedWithIC>true</isInitializedWithIC>
      <designMax>Inf</designMax>
      <designMin>-Inf</designMin>
      <originalPortNumber>14</originalPortNumber>
      <rateInfos type="ModelRefInfoRepo.RateInfo">
        <compiled>true</compiled>
        <period>.01</period>
        <priority>41</priority>
        <rateIdx>1</rateIdx>
        <taskedExplicitly>true</taskedExplicitly>
      </rateInfos>
      <resolvedSignalObject></resolvedSignalObject>
      <autosarInfo type="ModelRefInfoRepo.AUTOSAROutportInfo" uuid="0e8120a7-2be7-4a49-9f67-30b60daaf82f">
        <ElementName>VeOUT_DHM_RLDoorHandleLrnStsEE_sig</ElementName>
        <PortName>VeOUT_DHM_RLDoorHandleLrnStsEE_sig</PortName>
      </autosarInfo>
      <executionInterface type="ModelRefInfoRepo.OutputExecutionInterface" uuid="6fd855ca-678d-4fbf-8fe3-c95fce369464"/>
      <sigNameToEMVCEMap type="ModelRefInfoRepo.SigNameEMVCEInfo" uuid="2949ef9d-becf-4381-83b8-d9d330d4f97b"/>
    </outports>
    <outports type="ModelRefInfoRepo.OutportInformation" uuid="7a368d76-ed86-4adb-b2da-c03ec0c7ee48">
      <hasSystemInitMethod>true</hasSystemInitMethod>
      <isInitializedWithIC>true</isInitializedWithIC>
      <designMax>Inf</designMax>
      <designMin>-Inf</designMin>
      <originalPortNumber>15</originalPortNumber>
      <rateInfos type="ModelRefInfoRepo.RateInfo">
        <compiled>true</compiled>
        <period>.01</period>
        <priority>41</priority>
        <rateIdx>1</rateIdx>
        <taskedExplicitly>true</taskedExplicitly>
      </rateInfos>
      <resolvedSignalObject></resolvedSignalObject>
      <autosarInfo type="ModelRefInfoRepo.AUTOSAROutportInfo" uuid="adbd0429-ef0c-4d2a-b531-35035ec50fdd">
        <ElementName>VbOUT_DHM_DoorHandleLrnReq_flg</ElementName>
        <PortName>VbOUT_DHM_DoorHandleLrnReq_flg</PortName>
      </autosarInfo>
      <executionInterface type="ModelRefInfoRepo.OutputExecutionInterface" uuid="25e00d11-c8d5-46f7-8573-c1cfca948e1c"/>
      <sigNameToEMVCEMap type="ModelRefInfoRepo.SigNameEMVCEInfo" uuid="6159787f-572e-4d38-8863-18f1550f665e"/>
    </outports>
    <removeResetFunc>true</removeResetFunc>
    <runtimeNonFcnCallRateInfos type="ModelRefInfoRepo.RateInfo">
      <compiled>true</compiled>
      <isEmpty>true</isEmpty>
      <period>.01</period>
      <priority>40</priority>
      <rateIdx>0</rateIdx>
    </runtimeNonFcnCallRateInfos>
    <runtimeNonFcnCallRateInfos type="ModelRefInfoRepo.RateInfo">
      <compiled>true</compiled>
      <period>.01</period>
      <priority>41</priority>
      <rateIdx>1</rateIdx>
      <taskedExplicitly>true</taskedExplicitly>
    </runtimeNonFcnCallRateInfos>
    <sampleTimeInheritanceRule>2</sampleTimeInheritanceRule>
    <solverStatusFlags>323</solverStatusFlags>
    <standaloneEnumInfos type="ModelRefInfoRepo.StandaloneEnumInfo" uuid="3257946c-87f0-4e7f-b5f5-56ca39b49ade">
      <defaultValue>Hnd_Fold</defaultValue>
      <enumName>HndPos_Sts_E</enumName>
      <labels>Hnd_Fold</labels>
      <labels>Hnd_Unfold</labels>
      <labels>Hnd_Unknown</labels>
      <labels>Hnd_Reserved</labels>
      <storageType>uint8</storageType>
      <values>0</values>
      <values>1</values>
      <values>2</values>
      <values>3</values>
    </standaloneEnumInfos>
    <standaloneEnumInfos type="ModelRefInfoRepo.StandaloneEnumInfo" uuid="1d00e842-2ed6-4b22-8c19-6de627081270">
      <defaultValue>Door_Lock</defaultValue>
      <enumName>Door_Sts_E</enumName>
      <labels>Door_Lock</labels>
      <labels>Door_Unlock</labels>
      <labels>Door_Superlock</labels>
      <labels>Door_Unknown</labels>
      <storageType>uint8</storageType>
      <values>0</values>
      <values>1</values>
      <values>2</values>
      <values>3</values>
    </standaloneEnumInfos>
    <standaloneEnumInfos type="ModelRefInfoRepo.StandaloneEnumInfo" uuid="f5ea7d09-78b7-4a4e-82e1-aeb19babf88d">
      <defaultValue>Learn_Invalid</defaultValue>
      <enumName>Learn_Sts_E</enumName>
      <labels>Learn_Invalid</labels>
      <labels>Learn_Success</labels>
      <labels>Learn_Fail</labels>
      <labels>Learn_Reserved</labels>
      <storageType>uint8</storageType>
      <values>0</values>
      <values>1</values>
      <values>2</values>
      <values>3</values>
    </standaloneEnumInfos>
    <standaloneEnumInfos type="ModelRefInfoRepo.StandaloneEnumInfo" uuid="967b025d-4c7f-416f-8a12-2a7d68089141">
      <defaultValue>Gear_Reserved1</defaultValue>
      <enumName>Gear_Posn_E</enumName>
      <labels>Gear_Reserved1</labels>
      <labels>Gear_P</labels>
      <labels>Gear_R</labels>
      <labels>Gear_N</labels>
      <labels>Gear_D</labels>
      <labels>Gear_Reserved2</labels>
      <storageType>uint8</storageType>
      <values>0</values>
      <values>1</values>
      <values>2</values>
      <values>3</values>
      <values>4</values>
      <values>5</values>
    </standaloneEnumInfos>
    <timingAndTaskingRegistry>&lt;?xml version=&quot;1.0&quot;?&gt;
&lt;slexec_sto version=&quot;1.1&quot; packageUris=&quot;http://schema.mathworks.com/mf0/slexec_mm_sto/R2022a_202107291127&quot;&gt;
  &lt;sto.Registry type=&quot;sto.Registry&quot; uuid=&quot;2c4d726f-090b-4fd3-8050-c70ae65af893&quot;&gt;
    &lt;clocks type=&quot;sto.Timer&quot; uuid=&quot;aeb3dd80-7c76-453a-9ec8-46addaeed707&quot;&gt;
      &lt;computedFundamentalDiscretePeriod&gt;.01&lt;/computedFundamentalDiscretePeriod&gt;
      &lt;resolution&gt;.01&lt;/resolution&gt;
      &lt;clockTickConstraint&gt;PeriodicWithFixedResolution&lt;/clockTickConstraint&gt;
      &lt;rates type=&quot;sto.ClassicPeriodicDiscreteRate&quot; uuid=&quot;7564edab-d199-417d-8603-197b9ef2dec9&quot;&gt;
        &lt;annotation&gt;D1&lt;/annotation&gt;
        &lt;colorIndex&gt;2&lt;/colorIndex&gt;
        &lt;description&gt; 1&lt;/description&gt;
        &lt;taskId&gt;_task0&lt;/taskId&gt;
        &lt;rateSpec type=&quot;sto.RateSpec&quot; uuid=&quot;b5712fb3-1de2-4d47-846a-ce70ff2c92f4&quot;&gt;
          &lt;period&gt;.01&lt;/period&gt;
          &lt;rateType&gt;ClassicPeriodicDiscrete&lt;/rateType&gt;
        &lt;/rateSpec&gt;
      &lt;/rates&gt;
      &lt;rates type=&quot;sto.ClassicPeriodicDiscreteRate&quot; uuid=&quot;17b1f230-5a6e-4efa-a191-452a95186a4c&quot;&gt;
        &lt;annotation&gt;F0&lt;/annotation&gt;
        &lt;colorIndex&gt;2&lt;/colorIndex&gt;
        &lt;description&gt;&lt;/description&gt;
        &lt;rateIdx&gt;1&lt;/rateIdx&gt;
        &lt;taskId&gt;DHM_Step&lt;/taskId&gt;
        &lt;rateSpec type=&quot;sto.RateSpec&quot; uuid=&quot;b2e5a4be-4ca1-4228-8489-b5a3547611fb&quot;&gt;
          &lt;period&gt;.01&lt;/period&gt;
          &lt;rateType&gt;ClassicPeriodicDiscrete&lt;/rateType&gt;
        &lt;/rateSpec&gt;
      &lt;/rates&gt;
      &lt;timeAdvanceMode&gt;FixedStep&lt;/timeAdvanceMode&gt;
      &lt;baseRate type=&quot;sto.ClassicPeriodicDiscreteRate&quot; uuid=&quot;aefb2695-4b49-43fa-856c-bac5c28f9655&quot;&gt;
        &lt;annotation&gt;D1&lt;/annotation&gt;
        &lt;colorIndex&gt;2&lt;/colorIndex&gt;
        &lt;description&gt; 1&lt;/description&gt;
        &lt;taskId&gt;_task0&lt;/taskId&gt;
        &lt;rateSpec type=&quot;sto.RateSpec&quot; uuid=&quot;377ec217-c2b4-4fe5-909f-a834085ee8d4&quot;&gt;
          &lt;period&gt;.01&lt;/period&gt;
          &lt;rateType&gt;ClassicPeriodicDiscrete&lt;/rateType&gt;
        &lt;/rateSpec&gt;
      &lt;/baseRate&gt;
    &lt;/clocks&gt;
    &lt;clocks type=&quot;sto.Event&quot; uuid=&quot;262031fe-c43b-46ee-aaa3-dcafc9946570&quot;&gt;
      &lt;eventType&gt;POWER_UP_EVENT&lt;/eventType&gt;
      &lt;cNum&gt;1&lt;/cNum&gt;
      &lt;clockType&gt;Event&lt;/clockType&gt;
      &lt;identifier&gt;Init&lt;/identifier&gt;
      &lt;rates type=&quot;sto.ModelWideEventRate&quot; uuid=&quot;7f5294c4-0495-4ae0-a308-789618598bfa&quot;&gt;
        &lt;annotation&gt;Init&lt;/annotation&gt;
        &lt;clockId&gt;Init&lt;/clockId&gt;
        &lt;colorIndex&gt;10&lt;/colorIndex&gt;
        &lt;description&gt;&lt;/description&gt;
        &lt;rateIdx&gt;2&lt;/rateIdx&gt;
        &lt;taskId&gt;ModelWideInitializeEvent&lt;/taskId&gt;
        &lt;rateSpec type=&quot;sto.RateSpec&quot; uuid=&quot;e6934356-7675-44a7-b321-ce7465a92a02&quot;&gt;
          &lt;offset&gt;1.0&lt;/offset&gt;
          &lt;period&gt;Inf&lt;/period&gt;
          &lt;rateType&gt;ModelWideInitializeEvent&lt;/rateType&gt;
        &lt;/rateSpec&gt;
      &lt;/rates&gt;
      &lt;taskingMode&gt;ExplicitTasking&lt;/taskingMode&gt;
      &lt;timeAdvanceMode&gt;None&lt;/timeAdvanceMode&gt;
    &lt;/clocks&gt;
    &lt;clocks type=&quot;sto.Event&quot; uuid=&quot;dd6166ad-fbd1-4bbb-bbcc-0c68e136f5df&quot;&gt;
      &lt;eventType&gt;PARAMETER_CHANGE_EVENT&lt;/eventType&gt;
      &lt;cNum&gt;2&lt;/cNum&gt;
      &lt;clockType&gt;Event&lt;/clockType&gt;
      &lt;identifier&gt;ParameterChangeEvent&lt;/identifier&gt;
      &lt;rates type=&quot;sto.ModelWideEventRate&quot; uuid=&quot;37569312-7367-4cd6-a0cd-a616519fb84f&quot;&gt;
        &lt;clockId&gt;ParameterChangeEvent&lt;/clockId&gt;
        &lt;rateIdx&gt;-1&lt;/rateIdx&gt;
        &lt;taskId&gt;ModelWideParameterChangeEvent&lt;/taskId&gt;
        &lt;useForExecution&gt;NotForExecution&lt;/useForExecution&gt;
        &lt;rateSpec type=&quot;sto.RateSpec&quot; uuid=&quot;9998825f-3b7f-4f3e-8e0c-387370183aca&quot;&gt;
          &lt;period&gt;Inf&lt;/period&gt;
          &lt;rateType&gt;ModelWideParameterChangeEvent&lt;/rateType&gt;
        &lt;/rateSpec&gt;
      &lt;/rates&gt;
      &lt;taskingMode&gt;ExplicitTasking&lt;/taskingMode&gt;
      &lt;timeAdvanceMode&gt;None&lt;/timeAdvanceMode&gt;
    &lt;/clocks&gt;
    &lt;executionSpec&gt;Undetermined&lt;/executionSpec&gt;
    &lt;taskPriorityDirection&gt;HighNumberLast&lt;/taskPriorityDirection&gt;
    &lt;timeAdvanceMode&gt;FixedStep&lt;/timeAdvanceMode&gt;
    &lt;taskRegistry type=&quot;sto.TaskRegistry&quot; uuid=&quot;6158bf90-6d96-4493-a84d-cccf33175eae&quot;&gt;
      &lt;rootTaskHierarchyElements type=&quot;sto.Task&quot; uuid=&quot;f8cfafb1-31ec-47bb-b5e8-4292a52d2ec5&quot;&gt;
        &lt;isExecutable&gt;true&lt;/isExecutable&gt;
        &lt;rates type=&quot;sto.ClassicPeriodicDiscreteRate&quot; uuid=&quot;7efea167-0f5c-4d6d-acd0-81b2d8b1d80b&quot;&gt;
          &lt;annotation&gt;D1&lt;/annotation&gt;
          &lt;colorIndex&gt;2&lt;/colorIndex&gt;
          &lt;description&gt; 1&lt;/description&gt;
          &lt;taskId&gt;_task0&lt;/taskId&gt;
          &lt;rateSpec type=&quot;sto.RateSpec&quot; uuid=&quot;a5cef5b0-e7bc-4f8f-b72b-fe5521bdcc06&quot;&gt;
            &lt;period&gt;.01&lt;/period&gt;
            &lt;rateType&gt;ClassicPeriodicDiscrete&lt;/rateType&gt;
          &lt;/rateSpec&gt;
        &lt;/rates&gt;
        &lt;elementType&gt;Task&lt;/elementType&gt;
        &lt;identifier&gt;_task0&lt;/identifier&gt;
        &lt;priority&gt;40&lt;/priority&gt;
      &lt;/rootTaskHierarchyElements&gt;
      &lt;rootTaskHierarchyElements type=&quot;sto.Task&quot; uuid=&quot;1684ff3e-22df-4e45-913b-844a2a97d756&quot;&gt;
        &lt;isExecutable&gt;true&lt;/isExecutable&gt;
        &lt;isExplicit&gt;true&lt;/isExplicit&gt;
        &lt;rates type=&quot;sto.ClassicPeriodicDiscreteRate&quot; uuid=&quot;cd7a6faa-667e-426c-ac78-471f33114b90&quot;&gt;
          &lt;annotation&gt;F0&lt;/annotation&gt;
          &lt;colorIndex&gt;2&lt;/colorIndex&gt;
          &lt;description&gt;&lt;/description&gt;
          &lt;rateIdx&gt;1&lt;/rateIdx&gt;
          &lt;taskId&gt;DHM_Step&lt;/taskId&gt;
          &lt;rateSpec type=&quot;sto.RateSpec&quot; uuid=&quot;d8a2dc50-df6a-4b5e-bbad-662acddc97a4&quot;&gt;
            &lt;period&gt;.01&lt;/period&gt;
            &lt;rateType&gt;ClassicPeriodicDiscrete&lt;/rateType&gt;
          &lt;/rateSpec&gt;
        &lt;/rates&gt;
        &lt;tNum&gt;1&lt;/tNum&gt;
        &lt;elementType&gt;Task&lt;/elementType&gt;
        &lt;identifier&gt;DHM_Step&lt;/identifier&gt;
        &lt;priority&gt;41&lt;/priority&gt;
      &lt;/rootTaskHierarchyElements&gt;
      &lt;rootTaskHierarchyElements type=&quot;sto.Task&quot; uuid=&quot;866b85a1-dd0b-4c6b-b40e-52bae4c9e04f&quot;&gt;
        &lt;isExecutable&gt;true&lt;/isExecutable&gt;
        &lt;isExplicit&gt;true&lt;/isExplicit&gt;
        &lt;rates type=&quot;sto.ModelWideEventRate&quot; uuid=&quot;67569d01-19c0-48fa-a319-daf497130bcb&quot;&gt;
          &lt;annotation&gt;Init&lt;/annotation&gt;
          &lt;clockId&gt;Init&lt;/clockId&gt;
          &lt;colorIndex&gt;10&lt;/colorIndex&gt;
          &lt;description&gt;&lt;/description&gt;
          &lt;rateIdx&gt;2&lt;/rateIdx&gt;
          &lt;taskId&gt;ModelWideInitializeEvent&lt;/taskId&gt;
          &lt;rateSpec type=&quot;sto.RateSpec&quot; uuid=&quot;adabc0d2-91b8-434c-af54-b8f1275ac1d2&quot;&gt;
            &lt;offset&gt;1.0&lt;/offset&gt;
            &lt;period&gt;Inf&lt;/period&gt;
            &lt;rateType&gt;ModelWideInitializeEvent&lt;/rateType&gt;
          &lt;/rateSpec&gt;
        &lt;/rates&gt;
        &lt;tNum&gt;2&lt;/tNum&gt;
        &lt;elementType&gt;Task&lt;/elementType&gt;
        &lt;identifier&gt;ModelWideInitializeEvent&lt;/identifier&gt;
        &lt;priority&gt;-1&lt;/priority&gt;
        &lt;schedulingClockId&gt;Init&lt;/schedulingClockId&gt;
      &lt;/rootTaskHierarchyElements&gt;
      &lt;rootTaskHierarchyElements type=&quot;sto.Task&quot; uuid=&quot;6d90d026-5806-4cca-b4b2-f93d2606b559&quot;&gt;
        &lt;isExplicit&gt;true&lt;/isExplicit&gt;
        &lt;rates type=&quot;sto.ModelWideEventRate&quot; uuid=&quot;319d79f9-afea-4296-83a6-eee682f2fe21&quot;&gt;
          &lt;clockId&gt;ParameterChangeEvent&lt;/clockId&gt;
          &lt;rateIdx&gt;-1&lt;/rateIdx&gt;
          &lt;taskId&gt;ModelWideParameterChangeEvent&lt;/taskId&gt;
          &lt;useForExecution&gt;NotForExecution&lt;/useForExecution&gt;
          &lt;rateSpec type=&quot;sto.RateSpec&quot; uuid=&quot;8c658a9c-747e-4b83-88e6-1b2afd491105&quot;&gt;
            &lt;period&gt;Inf&lt;/period&gt;
            &lt;rateType&gt;ModelWideParameterChangeEvent&lt;/rateType&gt;
          &lt;/rateSpec&gt;
        &lt;/rates&gt;
        &lt;elementType&gt;Task&lt;/elementType&gt;
        &lt;identifier&gt;ModelWideParameterChangeEvent&lt;/identifier&gt;
        &lt;priority&gt;-1&lt;/priority&gt;
        &lt;schedulingClockId&gt;ParameterChangeEvent&lt;/schedulingClockId&gt;
      &lt;/rootTaskHierarchyElements&gt;
      &lt;taskDependencyGraph type=&quot;sto.SerializedTaskConnectionList&quot; uuid=&quot;bee7249c-3ee3-4563-b7b0-628e7b301094&quot;&gt;
        &lt;taskIdentifier&gt;_task0&lt;/taskIdentifier&gt;
      &lt;/taskDependencyGraph&gt;
      &lt;taskDependencyGraph type=&quot;sto.SerializedTaskConnectionList&quot; uuid=&quot;33618ded-be1d-48b6-8e0a-25cc5a4d21f3&quot;&gt;
        &lt;clockIdentifier&gt;Init&lt;/clockIdentifier&gt;
        &lt;taskIdentifier&gt;ModelWideInitializeEvent&lt;/taskIdentifier&gt;
      &lt;/taskDependencyGraph&gt;
      &lt;taskDependencyGraph type=&quot;sto.SerializedTaskConnectionList&quot; uuid=&quot;82e4c6cc-cb32-41e4-9639-bfd174e1dc50&quot;&gt;
        &lt;clockIdentifier&gt;ParameterChangeEvent&lt;/clockIdentifier&gt;
        &lt;taskIdentifier&gt;ModelWideParameterChangeEvent&lt;/taskIdentifier&gt;
      &lt;/taskDependencyGraph&gt;
      &lt;taskDependencyGraph type=&quot;sto.SerializedTaskConnectionList&quot; uuid=&quot;75a755e7-d1ba-4757-a2f3-a46be57f2d13&quot;&gt;
        &lt;taskIdentifier&gt;DHM_Step&lt;/taskIdentifier&gt;
      &lt;/taskDependencyGraph&gt;
    &lt;/taskRegistry&gt;
  &lt;/sto.Registry&gt;
&lt;/slexec_sto&gt;</timingAndTaskingRegistry>
    <zeroInternalMemoryAtStartupUnchecked>true</zeroInternalMemoryAtStartupUnchecked>
    <FMUBlockMap type="ModelRefInfoRepo.FMUBlockInfo" uuid="82798731-fa78-4d1a-9b28-fd3b1fa4aac5"/>
    <codeGenInfo type="ModelRefInfoRepo.CodeGenInformation" uuid="25bc6b6d-e21e-4f84-81aa-72e4bacbf022"/>
    <compiledVariantInfos type="ModelRefInfoRepo.CompiledVariantInfoMap" uuid="2c901307-1e86-465a-bc5f-39bbb3943576"/>
    <configSettingsForConsistencyChecks type="ModelRefInfoRepo.ConfigSettingsForConsistencyChecks" uuid="1237c786-da20-4376-92f0-275517d27cef">
      <consistentOutportInitialization>true</consistentOutportInitialization>
      <fixedStepSize>.01</fixedStepSize>
      <frameDiagnosticSetting>2</frameDiagnosticSetting>
      <hasHybridSampleTime>true</hasHybridSampleTime>
      <isExportFcnDiagram>true</isExportFcnDiagram>
      <isRateGrouped>true</isRateGrouped>
      <optimizedInitCode>true</optimizedInitCode>
      <signalLoggingSaveFormat>2</signalLoggingSaveFormat>
      <simSIMDOptimization>1</simSIMDOptimization>
      <solverMode>SOLVER_MODE_MULTITASKING</solverMode>
      <solverName>FixedStepDiscrete</solverName>
      <solverType>SOLVER_TYPE_FIXEDSTEP</solverType>
      <hardwareSettings type="ModelRefInfoRepo.HardwareSettings" uuid="de2ad531-49bb-43b1-9785-259a79f8c63e">
        <prodBitPerChar>8</prodBitPerChar>
        <prodBitPerDouble>64</prodBitPerDouble>
        <prodBitPerFloat>32</prodBitPerFloat>
        <prodBitPerInt>32</prodBitPerInt>
        <prodBitPerLong>32</prodBitPerLong>
        <prodBitPerLongLong>64</prodBitPerLongLong>
        <prodBitPerPointer>64</prodBitPerPointer>
        <prodBitPerPtrDiffT>64</prodBitPerPtrDiffT>
        <prodBitPerShort>16</prodBitPerShort>
        <prodBitPerSizeT>64</prodBitPerSizeT>
        <prodEndianess>1</prodEndianess>
        <prodShiftRight>true</prodShiftRight>
        <prodWordSize>64</prodWordSize>
      </hardwareSettings>
    </configSettingsForConsistencyChecks>
    <controllableInputRatesMap type="ModelRefInfoRepo.VarTsUIDMap" uuid="fbb5562a-3af0-4eb6-bd4d-0014b4f4f79b"/>
    <controllableOutputRatesMap type="ModelRefInfoRepo.VarTsUIDMap" uuid="a4b7339e-a395-4b49-bc59-5587f60960c5"/>
    <dataPortGroup type="ModelRefInfoRepo.DataPortGroup" uuid="03793c2c-1e87-4c31-9589-f8887bcf580d"/>
    <expFcnUnconnectedDataPortGroup type="ModelRefInfoRepo.DataPortGroup" uuid="80a66552-8622-426d-bb4a-d88f799d0ff0"/>
    <interfaceParameterInfo type="ModelRefInfoRepo.InterfaceParameterInfo" uuid="b960b8f0-bdbb-48b3-a317-3e63cec68141"/>
    <messageInfo type="ModelRefInfoRepo.MessageInformation" uuid="171d287a-1bbb-4281-8e22-e0409b758501">
      <rootInportInfo type="ModelRefInfoRepo.MessageRootPortInfo" uuid="284f0f03-d32e-47da-a245-091a465b6b7a">
        <GrHierarchyMsgModeMap type="ModelRefInfoRepo.MessageModeMap" uuid="cfc88e69-4495-476d-a257-90b0f0d96681">
          <portIdx>1</portIdx>
        </GrHierarchyMsgModeMap>
        <GrHierarchyMsgModeMap type="ModelRefInfoRepo.MessageModeMap" uuid="8360e6ea-09b2-4d1a-bcb2-a326f75547d2">
          <portIdx>13</portIdx>
        </GrHierarchyMsgModeMap>
        <GrHierarchyMsgModeMap type="ModelRefInfoRepo.MessageModeMap" uuid="4cd51a90-1064-4716-a82f-f20ed929c639">
          <portIdx>14</portIdx>
        </GrHierarchyMsgModeMap>
        <GrHierarchyMsgModeMap type="ModelRefInfoRepo.MessageModeMap" uuid="3532c084-2c6e-418e-b078-27e608ff2224">
          <portIdx>17</portIdx>
        </GrHierarchyMsgModeMap>
        <GrHierarchyMsgModeMap type="ModelRefInfoRepo.MessageModeMap" uuid="2fd7e1ee-b049-44b5-8f07-8b8b53c89ae5">
          <portIdx>18</portIdx>
        </GrHierarchyMsgModeMap>
      </rootInportInfo>
      <rootOutportInfo type="ModelRefInfoRepo.MessageRootPortInfo" uuid="f6aa9798-4416-48af-8349-73dc2f9c2e55">
        <GrHierarchyMsgModeMap type="ModelRefInfoRepo.MessageModeMap" uuid="53dbee56-4ce8-48ff-afa8-f5bc6c538e07">
          <portIdx>12</portIdx>
        </GrHierarchyMsgModeMap>
      </rootOutportInfo>
    </messageInfo>
    <methodInfo type="ModelRefInfoRepo.MethodExistenceInfo" uuid="52de8d19-f712-44c6-a27d-eab81712348f">
      <hasEnableMethod>true</hasEnableMethod>
      <hasSystemInitializeMethod>true</hasSystemInitializeMethod>
      <hasSystemResetMethod>true</hasSystemResetMethod>
      <hasTerminateMethod>true</hasTerminateMethod>
      <hasUpdateMethod>true</hasUpdateMethod>
    </methodInfo>
    <periodicEventPortUnsupportedBlockInfo type="ModelRefInfoRepo.PeriodicEventPortUnsupportedBlockInfo" uuid="118aba9a-667e-45b4-935a-3fc2775847ba"/>
    <portGroupsRequireSameRate type="ModelRefInfoRepo.PortGroupsRequireSameRate" uuid="eeacc293-b2b7-4d11-a16d-82d60a22be9d">
      <DSMPortGroups type="ModelRefInfoRepo.NameToPortGroupIdxVectMap" uuid="6cfc6e18-ad66-4dd3-9eca-eac22093f74b"/>
      <GlobalDSMPortGroups type="ModelRefInfoRepo.NameToPortGroupIdxVectMap" uuid="bf2c4855-335f-47b3-a245-ae816b54fc92"/>
      <mergedPortGroups type="ModelRefInfoRepo.NameToPortGroupIdxVectMap" uuid="7f18d06a-c4e7-4875-927e-70cbdaae0e0b"/>
    </portGroupsRequireSameRate>
    <rateBasedMdlGlobalDSMRateSpec type="ModelRefInfoRepo.GlobalDSMRateSpecMap" uuid="c164654b-26ef-48b7-8da7-bfbcb7728e6f"/>
    <rateSpecOfGlobalDSMAccessedByDescExpFcnMdlMap type="ModelRefInfoRepo.GlobalDSMRateSpecMap" uuid="734ca167-315c-45e5-b600-da93bd411c7e"/>
    <rootBlockDiagramInterface type="ci.Model" uuid="0dddd8df-f58d-42e6-8ef3-30f9681edfc7">
      <p_RootComponentInterface type="ci.ComponentInterface" uuid="7c173e04-365a-45dc-a574-6fd342ba38e4">
        <p_InputPorts type="ci.SignalInterface" uuid="0f6a5ec4-6fed-4fab-8d4f-73f5b00f2090">
          <p_ComputedNumericDimensions>1.0</p_ComputedNumericDimensions>
          <p_ComputedSampleTime>.01</p_ComputedSampleTime>
          <p_ComputedSampleTime>0.0</p_ComputedSampleTime>
          <p_ComputedType>fcn_call</p_ComputedType>
        </p_InputPorts>
        <p_InputPorts type="ci.SignalInterface" uuid="7ed56bb5-972d-4d60-8c41-6f66fb1fb0a0">
          <p_ComputedNumericDimensions>1.0</p_ComputedNumericDimensions>
          <p_ComputedSampleTime>.01</p_ComputedSampleTime>
          <p_ComputedSampleTime>0.0</p_ComputedSampleTime>
          <p_ComputedType>UInt8</p_ComputedType>
        </p_InputPorts>
        <p_InputPorts type="ci.SignalInterface" uuid="12b2e4e9-3abd-4ca2-8193-46c9fa6817f7">
          <p_ComputedNumericDimensions>1.0</p_ComputedNumericDimensions>
          <p_ComputedSampleTime>.01</p_ComputedSampleTime>
          <p_ComputedSampleTime>0.0</p_ComputedSampleTime>
          <p_ComputedType>UInt8</p_ComputedType>
        </p_InputPorts>
        <p_InputPorts type="ci.SignalInterface" uuid="eb1e2c54-4905-4db2-bae4-29a914dccc00">
          <p_ComputedNumericDimensions>1.0</p_ComputedNumericDimensions>
          <p_ComputedSampleTime>.01</p_ComputedSampleTime>
          <p_ComputedSampleTime>0.0</p_ComputedSampleTime>
          <p_ComputedType>UInt8</p_ComputedType>
        </p_InputPorts>
        <p_InputPorts type="ci.SignalInterface" uuid="089fd997-8c53-4052-a8ea-45fe4b5d9db1">
          <p_ComputedNumericDimensions>1.0</p_ComputedNumericDimensions>
          <p_ComputedSampleTime>.01</p_ComputedSampleTime>
          <p_ComputedSampleTime>0.0</p_ComputedSampleTime>
          <p_ComputedType>SInt16</p_ComputedType>
        </p_InputPorts>
        <p_InputPorts type="ci.SignalInterface" uuid="d3329a51-fb9e-45ac-b008-fe962b25888d">
          <p_ComputedNumericDimensions>1.0</p_ComputedNumericDimensions>
          <p_ComputedSampleTime>.01</p_ComputedSampleTime>
          <p_ComputedSampleTime>0.0</p_ComputedSampleTime>
          <p_ComputedType>SInt16</p_ComputedType>
        </p_InputPorts>
        <p_InputPorts type="ci.SignalInterface" uuid="daa8de0b-c02a-491a-b3dd-16352916eb0f">
          <p_ComputedNumericDimensions>1.0</p_ComputedNumericDimensions>
          <p_ComputedSampleTime>.01</p_ComputedSampleTime>
          <p_ComputedSampleTime>0.0</p_ComputedSampleTime>
          <p_ComputedType>UInt8</p_ComputedType>
        </p_InputPorts>
        <p_InputPorts type="ci.SignalInterface" uuid="10a3a5e4-0afa-468e-99da-430b9af3248a">
          <p_ComputedNumericDimensions>1.0</p_ComputedNumericDimensions>
          <p_ComputedSampleTime>.01</p_ComputedSampleTime>
          <p_ComputedSampleTime>0.0</p_ComputedSampleTime>
          <p_ComputedType>UInt8</p_ComputedType>
        </p_InputPorts>
        <p_InputPorts type="ci.SignalInterface" uuid="ef84cbab-df65-4b3f-88f7-46439a3e2e29">
          <p_ComputedNumericDimensions>1.0</p_ComputedNumericDimensions>
          <p_ComputedSampleTime>.01</p_ComputedSampleTime>
          <p_ComputedSampleTime>0.0</p_ComputedSampleTime>
          <p_ComputedType>UInt8</p_ComputedType>
        </p_InputPorts>
        <p_InputPorts type="ci.SignalInterface" uuid="61cda4f1-54be-41a3-bee6-f069047c2cc1">
          <p_ComputedNumericDimensions>1.0</p_ComputedNumericDimensions>
          <p_ComputedSampleTime>.01</p_ComputedSampleTime>
          <p_ComputedSampleTime>0.0</p_ComputedSampleTime>
          <p_ComputedType>UInt8</p_ComputedType>
        </p_InputPorts>
        <p_InputPorts type="ci.SignalInterface" uuid="400695cc-6ec0-481b-8a35-7537e7f08ae8">
          <p_ComputedNumericDimensions>1.0</p_ComputedNumericDimensions>
          <p_ComputedSampleTime>.01</p_ComputedSampleTime>
          <p_ComputedSampleTime>0.0</p_ComputedSampleTime>
          <p_ComputedType>UInt8</p_ComputedType>
        </p_InputPorts>
        <p_InputPorts type="ci.SignalInterface" uuid="6a7db46f-b32f-49ed-b8d7-0593088b7905">
          <p_ComputedNumericDimensions>1.0</p_ComputedNumericDimensions>
          <p_ComputedSampleTime>.01</p_ComputedSampleTime>
          <p_ComputedSampleTime>0.0</p_ComputedSampleTime>
          <p_ComputedType>UInt8</p_ComputedType>
        </p_InputPorts>
        <p_InputPorts type="ci.SignalInterface" uuid="5085829f-bc4a-48c3-9f26-4a575c4b5e6c">
          <p_ComputedNumericDimensions>1.0</p_ComputedNumericDimensions>
          <p_ComputedSampleTime>.01</p_ComputedSampleTime>
          <p_ComputedSampleTime>0.0</p_ComputedSampleTime>
          <p_ComputedType>Boolean</p_ComputedType>
        </p_InputPorts>
        <p_InputPorts type="ci.SignalInterface" uuid="00e78e6b-6ecf-4370-8d9d-5006deae511d">
          <p_ComputedNumericDimensions>1.0</p_ComputedNumericDimensions>
          <p_ComputedSampleTime>.01</p_ComputedSampleTime>
          <p_ComputedSampleTime>0.0</p_ComputedSampleTime>
          <p_ComputedType>SInt16</p_ComputedType>
        </p_InputPorts>
        <p_InputPorts type="ci.SignalInterface" uuid="eff36c02-82dd-46aa-84b3-cc3bee614cc1">
          <p_ComputedNumericDimensions>1.0</p_ComputedNumericDimensions>
          <p_ComputedSampleTime>.01</p_ComputedSampleTime>
          <p_ComputedSampleTime>0.0</p_ComputedSampleTime>
          <p_ComputedType>SInt16</p_ComputedType>
        </p_InputPorts>
        <p_InputPorts type="ci.SignalInterface" uuid="7cf7f3af-3de0-44a1-9781-febddfa573d0">
          <p_ComputedNumericDimensions>1.0</p_ComputedNumericDimensions>
          <p_ComputedSampleTime>.01</p_ComputedSampleTime>
          <p_ComputedSampleTime>0.0</p_ComputedSampleTime>
          <p_ComputedType>UInt8</p_ComputedType>
        </p_InputPorts>
        <p_InputPorts type="ci.SignalInterface" uuid="30bc9fb4-da0d-4515-910f-5f5520a28bfc">
          <p_ComputedNumericDimensions>1.0</p_ComputedNumericDimensions>
          <p_ComputedSampleTime>.01</p_ComputedSampleTime>
          <p_ComputedSampleTime>0.0</p_ComputedSampleTime>
          <p_ComputedType>UInt8</p_ComputedType>
        </p_InputPorts>
        <p_InputPorts type="ci.SignalInterface" uuid="7e4be201-2290-4ce8-b130-19669dbe134c">
          <p_ComputedNumericDimensions>1.0</p_ComputedNumericDimensions>
          <p_ComputedSampleTime>.01</p_ComputedSampleTime>
          <p_ComputedSampleTime>0.0</p_ComputedSampleTime>
          <p_ComputedType>UInt8</p_ComputedType>
        </p_InputPorts>
        <p_InputPorts type="ci.SignalInterface" uuid="2d789f03-4714-4e01-80dd-aba6894b0158">
          <p_ComputedNumericDimensions>1.0</p_ComputedNumericDimensions>
          <p_ComputedSampleTime>.01</p_ComputedSampleTime>
          <p_ComputedSampleTime>0.0</p_ComputedSampleTime>
          <p_ComputedType>UInt8</p_ComputedType>
        </p_InputPorts>
        <p_InputPorts type="ci.SignalInterface" uuid="e349d123-21ba-4d6c-8610-2ee8db3eeed3">
          <p_ComputedNumericDimensions>1.0</p_ComputedNumericDimensions>
          <p_ComputedSampleTime>.01</p_ComputedSampleTime>
          <p_ComputedSampleTime>0.0</p_ComputedSampleTime>
          <p_ComputedType>Boolean</p_ComputedType>
        </p_InputPorts>
        <p_Name>DHM</p_Name>
        <p_OutputPorts type="ci.SignalInterface" uuid="dacda3e2-2f70-44e7-8e34-148319c132f5">
          <p_ComputedNumericDimensions>1.0</p_ComputedNumericDimensions>
          <p_ComputedSampleTime>.01</p_ComputedSampleTime>
          <p_ComputedSampleTime>0.0</p_ComputedSampleTime>
          <p_ComputedType>UInt8</p_ComputedType>
        </p_OutputPorts>
        <p_OutputPorts type="ci.SignalInterface" uuid="3b9d3712-0730-42fd-ac03-e5ce1a16549c">
          <p_ComputedNumericDimensions>1.0</p_ComputedNumericDimensions>
          <p_ComputedSampleTime>.01</p_ComputedSampleTime>
          <p_ComputedSampleTime>0.0</p_ComputedSampleTime>
          <p_ComputedType>UInt8</p_ComputedType>
        </p_OutputPorts>
        <p_OutputPorts type="ci.SignalInterface" uuid="7b7ee4df-d4f2-4f14-bdd1-92b2dd15b189">
          <p_ComputedNumericDimensions>1.0</p_ComputedNumericDimensions>
          <p_ComputedSampleTime>.01</p_ComputedSampleTime>
          <p_ComputedSampleTime>0.0</p_ComputedSampleTime>
          <p_ComputedType>UInt8</p_ComputedType>
        </p_OutputPorts>
        <p_OutputPorts type="ci.SignalInterface" uuid="ad33d9f1-bbf3-4d5f-b127-ff286880a58d">
          <p_ComputedNumericDimensions>1.0</p_ComputedNumericDimensions>
          <p_ComputedSampleTime>.01</p_ComputedSampleTime>
          <p_ComputedSampleTime>0.0</p_ComputedSampleTime>
          <p_ComputedType>UInt8</p_ComputedType>
        </p_OutputPorts>
        <p_OutputPorts type="ci.SignalInterface" uuid="d915679f-f2dc-4155-b59a-25949c0b81cc">
          <p_ComputedNumericDimensions>1.0</p_ComputedNumericDimensions>
          <p_ComputedSampleTime>.01</p_ComputedSampleTime>
          <p_ComputedSampleTime>0.0</p_ComputedSampleTime>
          <p_ComputedType>UInt8</p_ComputedType>
        </p_OutputPorts>
        <p_OutputPorts type="ci.SignalInterface" uuid="ec811544-721a-47ba-ae6c-ffb54420b149">
          <p_ComputedNumericDimensions>1.0</p_ComputedNumericDimensions>
          <p_ComputedSampleTime>.01</p_ComputedSampleTime>
          <p_ComputedSampleTime>0.0</p_ComputedSampleTime>
          <p_ComputedType>UInt8</p_ComputedType>
        </p_OutputPorts>
        <p_OutputPorts type="ci.SignalInterface" uuid="7c8f57a3-8982-4822-bbd4-e6730e4fb12a">
          <p_ComputedNumericDimensions>1.0</p_ComputedNumericDimensions>
          <p_ComputedSampleTime>.01</p_ComputedSampleTime>
          <p_ComputedSampleTime>0.0</p_ComputedSampleTime>
          <p_ComputedType>Boolean</p_ComputedType>
        </p_OutputPorts>
        <p_OutputPorts type="ci.SignalInterface" uuid="4b7bb64b-1bb0-44c2-a561-3d163d4c8cba">
          <p_ComputedNumericDimensions>1.0</p_ComputedNumericDimensions>
          <p_ComputedSampleTime>.01</p_ComputedSampleTime>
          <p_ComputedSampleTime>0.0</p_ComputedSampleTime>
          <p_ComputedType>Boolean</p_ComputedType>
        </p_OutputPorts>
        <p_OutputPorts type="ci.SignalInterface" uuid="2fe85d4e-c532-4cb8-8b69-f04a78ff7612">
          <p_ComputedNumericDimensions>1.0</p_ComputedNumericDimensions>
          <p_ComputedSampleTime>.01</p_ComputedSampleTime>
          <p_ComputedSampleTime>0.0</p_ComputedSampleTime>
          <p_ComputedType>Boolean</p_ComputedType>
        </p_OutputPorts>
        <p_OutputPorts type="ci.SignalInterface" uuid="aaeb9ba2-c9e8-4e78-803b-739fe232918e">
          <p_ComputedNumericDimensions>1.0</p_ComputedNumericDimensions>
          <p_ComputedSampleTime>.01</p_ComputedSampleTime>
          <p_ComputedSampleTime>0.0</p_ComputedSampleTime>
          <p_ComputedType>Boolean</p_ComputedType>
        </p_OutputPorts>
        <p_OutputPorts type="ci.SignalInterface" uuid="d5d663d8-71c9-43f9-b5a6-6f8c6a58bef2">
          <p_ComputedNumericDimensions>1.0</p_ComputedNumericDimensions>
          <p_ComputedSampleTime>.01</p_ComputedSampleTime>
          <p_ComputedSampleTime>0.0</p_ComputedSampleTime>
          <p_ComputedType>SInt16</p_ComputedType>
        </p_OutputPorts>
        <p_OutputPorts type="ci.SignalInterface" uuid="fa133a50-daad-4786-866e-b7e1078d223c">
          <p_ComputedNumericDimensions>1.0</p_ComputedNumericDimensions>
          <p_ComputedSampleTime>.01</p_ComputedSampleTime>
          <p_ComputedSampleTime>0.0</p_ComputedSampleTime>
          <p_ComputedType>SInt16</p_ComputedType>
        </p_OutputPorts>
        <p_OutputPorts type="ci.SignalInterface" uuid="a890e7c0-7d2e-4f95-87ac-c6c71c20c869">
          <p_ComputedNumericDimensions>1.0</p_ComputedNumericDimensions>
          <p_ComputedSampleTime>.01</p_ComputedSampleTime>
          <p_ComputedSampleTime>0.0</p_ComputedSampleTime>
          <p_ComputedType>UInt8</p_ComputedType>
        </p_OutputPorts>
        <p_OutputPorts type="ci.SignalInterface" uuid="6125be93-1fbd-4639-890f-fe099c33f2a7">
          <p_ComputedNumericDimensions>1.0</p_ComputedNumericDimensions>
          <p_ComputedSampleTime>.01</p_ComputedSampleTime>
          <p_ComputedSampleTime>0.0</p_ComputedSampleTime>
          <p_ComputedType>UInt8</p_ComputedType>
        </p_OutputPorts>
        <p_OutputPorts type="ci.SignalInterface" uuid="788d2834-35f4-4785-a35e-c63c80d48870">
          <p_ComputedNumericDimensions>1.0</p_ComputedNumericDimensions>
          <p_ComputedSampleTime>.01</p_ComputedSampleTime>
          <p_ComputedSampleTime>0.0</p_ComputedSampleTime>
          <p_ComputedType>UInt8</p_ComputedType>
        </p_OutputPorts>
        <p_OutputPorts type="ci.SignalInterface" uuid="5a704b8b-c614-4c4b-9b7f-c16c54706c63">
          <p_ComputedNumericDimensions>1.0</p_ComputedNumericDimensions>
          <p_ComputedSampleTime>.01</p_ComputedSampleTime>
          <p_ComputedSampleTime>0.0</p_ComputedSampleTime>
          <p_ComputedType>Boolean</p_ComputedType>
        </p_OutputPorts>
        <p_Type>ROOT</p_Type>
      </p_RootComponentInterface>
    </rootBlockDiagramInterface>
    <simulinkFunctions type="ModelRefInfoRepo.SimulinkFunctions" uuid="1e4eb837-48be-4a33-9f9f-e0f7e629dfdd">
      <compSimulinkFunctionCatalog></compSimulinkFunctionCatalog>
    </simulinkFunctions>
    <stateWriterToOwnerMap type="ModelRefInfoRepo.StateWriterInfo" uuid="17a115a7-adaa-4221-95a2-8274d235c3ff"/>
    <stoClientDataRegistry type="sto.ClientDataRegistry" uuid="96f40bbd-2f82-4cbc-a855-e56700da92df">
      <dataSets type="sto.ClientClockNamedDataSet" uuid="d6224c9d-eacf-4f45-ac39-6b474f5c2246">
        <tag>sltpEvents</tag>
      </dataSets>
      <dataSets type="sto.ClientTaskHierarchyElementNamedDataSet" uuid="458ec136-d436-45d6-98d6-8e19cbbe5895">
        <tag>sltpTaskGroups</tag>
      </dataSets>
      <dataSets type="sto.ClientTaskHierarchyElementNamedDataSet" uuid="c779c9bb-9f86-4502-af5a-d72a9a79271c">
        <dSet type="ModelRefInfoRepo.SltpTaskData" uuid="f4695412-7052-401b-a244-c186fc9dddb7"/>
        <tSet type="ModelRefInfoRepo.SltpTaskData" uuid="f4695412-7052-401b-a244-c186fc9dddb7">
          <dataName>DHM_Step</dataName>
          <linkedSet type="sto.ClientTaskHierarchyElementNamedDataSet" uuid="c779c9bb-9f86-4502-af5a-d72a9a79271c"/>
          <id type="sto.TaskHierarchyElementId">
            <id>DHM_Step</id>
          </id>
        </tSet>
        <tag>sltpTasks</tag>
      </dataSets>
    </stoClientDataRegistry>
    <varTsUIDMap type="ModelRefInfoRepo.VarTsUIDMap" uuid="70a9f257-7e94-4c84-8205-0bcef9923285"/>
  </ModelRefInfoRepo.ModelRefInfoRoot>
</MF0>